{
  "18512": {
    "de": "",
    "en": "",
    "es": "",
    "fr": "",
    "it": "",
    "ja": "<start_lip_sync n01418 _normal m00001>「ああっ！　大変だよ！\n　大変なことに　なっちゃった！<stop_lip_animation n01418 CLOSE_MOUTH>",
    "ko": "<start_lip_sync n01418 _normal m00001>: 아앗! 큰일 났어!\n　엄청난 일이 벌어졌어!<stop_lip_animation n01418 CLOSE_MOUTH>",
    "zh-hans": "<start_lip_sync n01418 _normal m00001>啊啊！糟糕啦！\n出大麻烦啦！<stop_lip_animation n01418 CLOSE_MOUTH>",
    "zh-hant": "<start_lip_sync n01418 _normal m00001>啊啊！不好啦！\n大事不妙啦！<stop_lip_animation n01418 CLOSE_MOUTH>"
  },
  "18513": {
    "de": "",
    "en": "",
    "es": "",
    "fr": "",
    "it": "",
    "ja": "<start_lip_sync n01418 _normal m00001>「王さまが　大軍を率いて　行っちゃったの！\n　博士さんも　行っちゃった！<stop_lip_animation n01418 CLOSE_MOUTH>",
    "ko": "<start_lip_sync n01418 _normal m00001>: 왕께서 대군을 이끌고 가셨대!\n　박사님도 갔어!<stop_lip_animation n01418 CLOSE_MOUTH>",
    "zh-hans": "<start_lip_sync n01418 _normal m00001>国王陛下率领大军出发了！\n博士姐姐也跟去了啊！<stop_lip_animation n01418 CLOSE_MOUTH>",
    "zh-hant": "<start_lip_sync n01418 _normal m00001>國王率領大軍出發了！\n博士姊姊也跟去了啊！<stop_lip_animation n01418 CLOSE_MOUTH>"
  },
  "18514": {
    "de": "",
    "en": "",
    "es": "",
    "fr": "",
    "it": "",
    "ja": "<start_lip_sync n01418 _normal m00001>「うう……。暗黒大樹に　行ったんだよ。\n　ボク　兵士さんの話を聞いたんだ。<stop_lip_animation n01418 CLOSE_MOUTH>",
    "ko": "<start_lip_sync n01418 _normal m00001>: 으으……. 암흑거목으로 간 거야.\n　내가 병사한테 들었어.<stop_lip_animation n01418 CLOSE_MOUTH>",
    "zh-hans": "<start_lip_sync n01418 _normal m00001>呜呜……我听到士兵哥哥说，\n他们往黑暗大树去了啊。<stop_lip_animation n01418 CLOSE_MOUTH>",
    "zh-hant": "<start_lip_sync n01418 _normal m00001>嗚嗚……我聽到士兵哥哥說，\n他們往黑暗大樹去了。<stop_lip_animation n01418 CLOSE_MOUTH>"
  },
  "18515": {
    "de": "",
    "en": "",
    "es": "",
    "fr": "",
    "it": "",
    "ja": "<start_lip_sync n01418 _normal m00001>「暗黒大樹を　破壊しにいくって！<stop_lip_animation n01418 CLOSE_MOUTH>",
    "ko": "<start_lip_sync n01418 _normal m00001>: 암흑거목을 파괴하러 간대!<stop_lip_animation n01418 CLOSE_MOUTH>",
    "zh-hans": "<start_lip_sync n01418 _normal m00001>说是要破坏掉黑暗大树啊！<stop_lip_animation n01418 CLOSE_MOUTH>",
    "zh-hant": "<start_lip_sync n01418 _normal m00001>說是要破壞黑暗大樹！<stop_lip_animation n01418 CLOSE_MOUTH>"
  },
  "18516": {
    "de": "",
    "en": "",
    "es": "",
    "fr": "",
    "it": "",
    "ja": "<start_lip_sync n01418 _normal m00001>「ボ…ボク　イヤだよ。\n　博士さんも　パパも　みんな　いい人なのに……<stop_lip_animation n01418 CLOSE_MOUTH>",
    "ko": "<start_lip_sync n01418 _normal m00001>: 나… 나는 싫어.\n　박사님도 아빠도 다 좋은 사람인데……<stop_lip_animation n01418 CLOSE_MOUTH>",
    "zh-hans": "<start_lip_sync n01418 _normal m00001>我……我不要啊。\n明明博士姐姐和爸爸都是好人……<stop_lip_animation n01418 CLOSE_MOUTH>",
    "zh-hant": "<start_lip_sync n01418 _normal m00001>我……我不要這樣。\n明明博士姊姊和爸爸都是好人……<stop_lip_animation n01418 CLOSE_MOUTH>"
  },
  "18517": {
    "de": "",
    "en": "",
    "es": "",
    "fr": "",
    "it": "",
    "ja": "<start_lip_sync n01418 _normal m00001>「エルフと　大樹の番人が\n　戦うなんて　おかしいよ。<stop_lip_animation n01418 CLOSE_MOUTH>",
    "ko": "<start_lip_sync n01418 _normal m00001>: 엘프랑 거목의 파수꾼이\n　싸우는 건 이상해.<stop_lip_animation n01418 CLOSE_MOUTH>",
    "zh-hans": "<start_lip_sync n01418 _normal m00001>埃尔夫要和大树的看守作战，\n这太不正常了啊。<stop_lip_animation n01418 CLOSE_MOUTH>",
    "zh-hant": "<start_lip_sync n01418 _normal m00001>艾爾芙要和大樹看守戰鬥，\n這太不正常了啊。<stop_lip_animation n01418 CLOSE_MOUTH>"
  },
  "18518": {
    "de": "",
    "en": "",
    "es": "",
    "fr": "",
    "it": "",
    "ja": "<start_lip_sync n01418 _normal m00001>「ね…ねえ　ボクを\n　暗黒大樹に　連れてって。<stop_lip_animation n01418 CLOSE_MOUTH>",
    "ko": "<start_lip_sync n01418 _normal m00001>: 저… 저기 날\n　암흑거목으로 데려다줘.<stop_lip_animation n01418 CLOSE_MOUTH>",
    "zh-hans": "<start_lip_sync n01418 _normal m00001>求……\n求你带我去黑暗大树那里吧。<stop_lip_animation n01418 CLOSE_MOUTH>",
    "zh-hant": "<start_lip_sync n01418 _normal m00001>那……那個，\n帶我去黑暗大樹那裡吧。<stop_lip_animation n01418 CLOSE_MOUTH>"
  },
  "18519": {
    "de": "",
    "en": "",
    "es": "",
    "fr": "",
    "it": "",
    "ja": "<start_lip_sync n01418 _normal m00001>「ボク　戦いを止めたいんだ。\n　お…お願いします。<stop_lip_animation n01418 CLOSE_MOUTH>",
    "ko": "<start_lip_sync n01418 _normal m00001>: 난 그 싸움을 막고 싶어.\n　부… 부탁이야.<stop_lip_animation n01418 CLOSE_MOUTH>",
    "zh-hans": "<start_lip_sync n01418 _normal m00001>我要阻止战争。\n求……求你了。<stop_lip_animation n01418 CLOSE_MOUTH>",
    "zh-hant": "<start_lip_sync n01418 _normal m00001>我要阻止戰爭。\n拜……拜託你了。<stop_lip_animation n01418 CLOSE_MOUTH>"
  },
  "26333": {
    "de": "",
    "en": "",
    "es": "",
    "fr": "",
    "it": "",
    "ja": "クエストを　依頼されました。\nこのクエストを　受けますか？\n<select>\nうける\nやめる\n<select_end><close>",
    "ko": "퀘스트 의뢰를 받았습니다.\n이 퀘스트를 수락하겠습니까?\n<select>\n수락하기\n그만두기\n<select_end><close>",
    "zh-hans": "对方委托了任务。\n要接受这个任务吗？\n<select>\n接受\n放弃\n<select_end><close>",
    "zh-hant": "對方提出了任務委託。\n是否要承接這件任務？\n<select>\n承接\n放棄\n<select_end><close>"
  },
  "18520": {
    "de": "",
    "en": "",
    "es": "",
    "fr": "",
    "it": "",
    "ja": "<start_lip_sync n01418 _normal m00001>「あ…ありがと！\n　ボクの頼みを　聞いてくれて！<stop_lip_animation n01418 CLOSE_MOUTH>",
    "ko": "<start_lip_sync n01418 _normal m00001>: 고… 고마워!\n　내 부탁을 들어줘서!<stop_lip_animation n01418 CLOSE_MOUTH>",
    "zh-hans": "<start_lip_sync n01418 _normal m00001>谢……谢谢你！\n谢谢你愿意带我去！<stop_lip_animation n01418 CLOSE_MOUTH>",
    "zh-hant": "<start_lip_sync n01418 _normal m00001>謝……謝謝你！\n謝謝你願意帶我去！<stop_lip_animation n01418 CLOSE_MOUTH>"
  },
  "18521": {
    "de": "",
    "en": "",
    "es": "",
    "fr": "",
    "it": "",
    "ja": "<start_lip_sync n01418 _normal m00001>「ボク　後から　ついていくね！<stop_lip_animation n01418 CLOSE_MOUTH>",
    "ko": "<start_lip_sync n01418 _normal m00001>: 난 나중에 따라갈게!<stop_lip_animation n01418 CLOSE_MOUTH>",
    "zh-hans": "<start_lip_sync n01418 _normal m00001>我会跟在你后面的！<stop_lip_animation n01418 CLOSE_MOUTH>",
    "zh-hant": "<start_lip_sync n01418 _normal m00001>我會跟在你後面的！<stop_lip_animation n01418 CLOSE_MOUTH>"
  },
  "26332": {
    "de": "",
    "en": "",
    "es": "",
    "fr": "",
    "it": "",
    "ja": "クエスト『<%sEV_QUEST_NAME>』を\n受けました。<me 74>",
    "ko": "퀘스트\n『{%sEV_QUEST_NAME}|hpp(』을,』를)\n수락했습니다.<me 74>",
    "zh-hans": "已承接\n任务“<%sEV_QUEST_NAME>”。<me 74>",
    "zh-hant": "承接了\n任務「<%sEV_QUEST_NAME>」。<me 74>"
  },
  "18522": {
    "de": "",
    "en": "",
    "es": "",
    "fr": "",
    "it": "",
    "ja": "<start_lip_sync n01418 _normal m00001>「あ…ありがと！\n　でも　ほかの人たちの頼まれごとで\n　なんだか　いっぱいみたい……。<stop_lip_animation n01418 CLOSE_MOUTH>",
    "ko": "<start_lip_sync n01418 _normal m00001>: 고… 고마워!\n　근데 다른 사람들의 부탁 때문에\n　여유가 없어 보이네…….<stop_lip_animation n01418 CLOSE_MOUTH>",
    "zh-hans": "<start_lip_sync n01418 _normal m00001>谢……谢谢你！\n不过你好像还有很多\n别人的委托……<stop_lip_animation n01418 CLOSE_MOUTH>",
    "zh-hant": "<start_lip_sync n01418 _normal m00001>謝……謝謝你！\n不過你好像還有很多\n別人的委託……<stop_lip_animation n01418 CLOSE_MOUTH>"
  },
  "18523": {
    "de": "",
    "en": "",
    "es": "",
    "fr": "",
    "it": "",
    "ja": "<start_lip_sync n01418 _normal m00001>「は…早くしないと　戦いが始まっちゃう！\n　用事が済んだら　すぐに戻ってきてね！<stop_lip_animation n01418 CLOSE_MOUTH>",
    "ko": "<start_lip_sync n01418 _normal m00001>: 서… 서두르지 않으면 싸움이 시작될 거야!\n　볼일이 끝나면 곧바로 돌아와!<stop_lip_animation n01418 CLOSE_MOUTH>",
    "zh-hans": "<start_lip_sync n01418 _normal m00001>不……不快点去的话，战争就要开始了！\n把事办完，赶紧回来吧！<stop_lip_animation n01418 CLOSE_MOUTH>",
    "zh-hant": "<start_lip_sync n01418 _normal m00001>不……不快點去的話，戰爭就要開始了！\n你把事辦完就趕緊回來吧！<stop_lip_animation n01418 CLOSE_MOUTH>"
  },
  "18524": {
    "de": "",
    "en": "",
    "es": "",
    "fr": "",
    "it": "",
    "ja": "<start_lip_sync n01418 _normal m00001>「そ…そんな。\n　早くしないと　戦いが始まっちゃう……。<stop_lip_animation n01418 CLOSE_MOUTH>",
    "ko": "<start_lip_sync n01418 _normal m00001>: 그… 그럼 어쩌지.\n　서두르지 않으면 싸움이 시작될 텐데…….<stop_lip_animation n01418 CLOSE_MOUTH>",
    "zh-hans": "<start_lip_sync n01418 _normal m00001>怎……怎么这样啊……\n不快点阻止的话，战争就要开始了……<stop_lip_animation n01418 CLOSE_MOUTH>",
    "zh-hant": "<start_lip_sync n01418 _normal m00001>怎……怎麼這樣……\n不快點阻止的話，戰爭就要開始了……<stop_lip_animation n01418 CLOSE_MOUTH>"
  },
  "18525": {
    "de": "",
    "en": "",
    "es": "",
    "fr": "",
    "it": "",
    "ja": "<start_lip_sync n01418 _normal m00001>「でも　ほかに頼める人がいないし\n　ど…どうすればいいんだろ。<stop_lip_animation n01418 CLOSE_MOUTH>",
    "ko": "<start_lip_sync n01418 _normal m00001>: 그치만 달리 부탁할 사람도 없고\n　어… 어쩌면 좋지.<stop_lip_animation n01418 CLOSE_MOUTH>",
    "zh-hans": "<start_lip_sync n01418 _normal m00001>我也不认识其他人可以带我去，\n要……要怎么办才好啊。<stop_lip_animation n01418 CLOSE_MOUTH>",
    "zh-hant": "<start_lip_sync n01418 _normal m00001>可是，我又沒有其他人可以拜託，\n該……該怎麼辦才好……<stop_lip_animation n01418 CLOSE_MOUTH>"
  },
  "18526": {
    "de": "",
    "en": "",
    "es": "",
    "fr": "",
    "it": "",
    "ja": "<start_lip_sync n00943 _normal m00001>「ニコロイ王は　ご不在だ。\n　すまないが　また後で来てくれ。<stop_lip_animation n00943 CLOSE_MOUTH>",
    "ko": "<start_lip_sync n00943 _normal m00001>: 니코로이 왕께서는 부재중이시다.\n　미안하지만 나중에 다시 와.<stop_lip_animation n00943 CLOSE_MOUTH>",
    "zh-hans": "<start_lip_sync n00943 _normal m00001>尼克罗伊王不在城内。\n请回吧。<stop_lip_animation n00943 CLOSE_MOUTH>",
    "zh-hant": "<start_lip_sync n00943 _normal m00001>尼克羅伊王不在城內。\n不好意思，請之後再來吧。<stop_lip_animation n00943 CLOSE_MOUTH>"
  },
  "18527": {
    "de": "",
    "en": "",
    "es": "",
    "fr": "",
    "it": "",
    "ja": "<start_lip_sync n01418 _normal m00001>「ボク　エルフたちと\n　大樹の番人が戦うのを　止めたい。\n　ボ…ボクを　暗黒大樹に連れてって。<stop_lip_animation n01418 CLOSE_MOUTH>",
    "ko": "<start_lip_sync n01418 _normal m00001>: 난 엘프들과\n　거목의 파수꾼이 싸우는 걸 막고 싶어.\n　나… 나를 암흑거목으로 데려다줘.<stop_lip_animation n01418 CLOSE_MOUTH>",
    "zh-hans": "<start_lip_sync n01418 _normal m00001>我……\n想阻止埃尔夫们和大树的看守作战。\n请……请把我带到黑暗大树那里去吧。<stop_lip_animation n01418 CLOSE_MOUTH>",
    "zh-hant": "<start_lip_sync n01418 _normal m00001>我想阻止\n艾爾芙們和大樹看守戰鬥。\n請……請帶我去黑暗大樹那裡吧。<stop_lip_animation n01418 CLOSE_MOUTH>"
  },
  "18528": {
    "de": "",
    "en": "",
    "es": "",
    "fr": "",
    "it": "",
    "ja": "<start_lip_sync n01418 _normal m00001>「あ…暗黒大樹の場所は　覚えてる？\n　城を出たら　北へ進んで\n　カミハルムイ領北に　出るの。<stop_lip_animation n01418 CLOSE_MOUTH>",
    "ko": "<start_lip_sync n01418 _normal m00001>: 아… 암흑거목이 어딘지 기억나?\n　성을 나가 북쪽으로 가서\n　카미하루무이령 북부로 가면 돼.<stop_lip_animation n01418 CLOSE_MOUTH>",
    "zh-hans": "<start_lip_sync n01418 _normal m00001>啊……还记得黑暗大树在哪里吗？\n出城后往北走，\n离开神春无为北部领土。<stop_lip_animation n01418 CLOSE_MOUTH>",
    "zh-hant": "<start_lip_sync n01418 _normal m00001>還……還記得黑暗大樹在哪裡嗎？\n出城後往北走，\n就會到卡密哈爾姆領土北部。<stop_lip_animation n01418 CLOSE_MOUTH>"
  },
  "18529": {
    "de": "",
    "en": "",
    "es": "",
    "fr": "",
    "it": "",
    "ja": "<start_lip_sync n01418 _normal m00001>「北西に進んで　落陽の草原に着いたら\n　西に　まっすぐ進むんだよ。<stop_lip_animation n01418 CLOSE_MOUTH>",
    "ko": "<start_lip_sync n01418 _normal m00001>: 북서쪽으로 가서 낙양의 초원에 도착하면\n　서쪽으로 곧장 가는 거야.<stop_lip_animation n01418 CLOSE_MOUTH>",
    "zh-hans": "<start_lip_sync n01418 _normal m00001>再往西北方走，\n到达落日草原之后向西一直走。<stop_lip_animation n01418 CLOSE_MOUTH>",
    "zh-hant": "<start_lip_sync n01418 _normal m00001>再往西北方抵達落日草原後，\n就朝著西邊一直走。<stop_lip_animation n01418 CLOSE_MOUTH>"
  },
  "18530": {
    "de": "",
    "en": "",
    "es": "",
    "fr": "",
    "it": "",
    "ja": "<start_lip_sync n01418 _normal m00001>「ボク　後をついてくから\n　よ…よろしくね。<stop_lip_animation n01418 CLOSE_MOUTH>",
    "ko": "<start_lip_sync n01418 _normal m00001>: 나도 금방 따라갈 테니까\n　자… 잘 부탁해.<stop_lip_animation n01418 CLOSE_MOUTH>",
    "zh-hans": "<start_lip_sync n01418 _normal m00001>我也跟你一起去。\n请……请多关照了。<stop_lip_animation n01418 CLOSE_MOUTH>",
    "zh-hant": "<start_lip_sync n01418 _normal m00001>我會跟在你後面的，\n請……請多關照了。<stop_lip_animation n01418 CLOSE_MOUTH>"
  },
  "18531": {
    "de": "",
    "en": "",
    "es": "",
    "fr": "",
    "it": "",
    "ja": "<start_lip_sync n00133 _normal m00001>「そなたが　ここの長だな？<stop_lip_animation n00133 CLOSE_MOUTH>",
    "ko": "<start_lip_sync n00133 _normal m00001>: 그대가 이곳의 대장이렷다?<stop_lip_animation n00133 CLOSE_MOUTH>",
    "zh-hans": "<start_lip_sync n00133 _normal m00001>尊驾就是此地之长吗？<stop_lip_animation n00133 CLOSE_MOUTH>",
    "zh-hant": "<start_lip_sync n00133 _normal m00001>尊駕就是此地的長老嗎？<stop_lip_animation n00133 CLOSE_MOUTH>"
  },
  "18532": {
    "de": "",
    "en": "",
    "es": "",
    "fr": "",
    "it": "",
    "ja": "<start_lip_sync m50042 _normal m00001>「そうだ　エルフの王。<stop_lip_animation m50042 CLOSE_MOUTH>",
    "ko": "<start_lip_sync m50042 _normal m00001>: 그렇다. 엘프의 왕.<stop_lip_animation m50042 CLOSE_MOUTH>",
    "zh-hans": "<start_lip_sync m50042 _normal m00001>不错，埃尔夫之王。<stop_lip_animation m50042 CLOSE_MOUTH>",
    "zh-hant": "<start_lip_sync m50042 _normal m00001>沒錯，艾爾芙之王。<stop_lip_animation m50042 CLOSE_MOUTH>"
  },
  "18533": {
    "de": "",
    "en": "",
    "es": "",
    "fr": "",
    "it": "",
    "ja": "<start_lip_sync n00133 _normal m00001>「暗黒大樹の長よ……。聞いてくれ。\n　今　暗黒大樹が活性化し\n　各地で　魔瘴が　次々と発生しているのだ。<stop_lip_animation n00133 CLOSE_MOUTH>",
    "ko": "<start_lip_sync n00133 _normal m00001>: 암흑거목 대장이여……. 들어 다오.\n　지금 암흑거목의 활성화로 인해\n　각지에서 마장이 잇달아 발생하고 있다.<stop_lip_animation n00133 CLOSE_MOUTH>",
    "zh-hans": "<start_lip_sync n00133 _normal m00001>黑暗大树之长啊……请听我一言。\n如今黑暗大树日渐活性化，\n各地不断出现魔瘴。<stop_lip_animation n00133 CLOSE_MOUTH>",
    "zh-hant": "<start_lip_sync n00133 _normal m00001>黑暗大樹的長老……請聽我一言。\n如今黑暗大樹日漸活化，\n各地接連地出現魔瘴。<stop_lip_animation n00133 CLOSE_MOUTH>"
  },
  "18534": {
    "de": "",
    "en": "",
    "es": "",
    "fr": "",
    "it": "",
    "ja": "<start_lip_sync n00133 _normal m00001>「このままでは　遠からず\n　エルトナ大陸は　魔瘴により　滅びるだろう。\n　滅びから逃れる方法は　ひとつしかない。<stop_lip_animation n00133 CLOSE_MOUTH>",
    "ko": "<start_lip_sync n00133 _normal m00001>: 이러다가는 머지않아\n　엘토나 대륙이 마장 때문에 멸망할 것이다.\n　멸망을 피할 방법은 오직 하나.<stop_lip_animation n00133 CLOSE_MOUTH>",
    "zh-hans": "<start_lip_sync n00133 _normal m00001>如此下去，\n不久之后埃尔托纳大陆就会被魔瘴毁掉。\n若要逃脱此命运，只有一个方法。<stop_lip_animation n00133 CLOSE_MOUTH>",
    "zh-hant": "<start_lip_sync n00133 _normal m00001>再這樣下去，\n艾爾托納大陸不久就會因魔瘴而毀滅吧。\n若要逃離毀滅的命運，方法只有一個。<stop_lip_animation n00133 CLOSE_MOUTH>"
  },
  "18535": {
    "de": "",
    "en": "",
    "es": "",
    "fr": "",
    "it": "",
    "ja": "<start_lip_sync n00133 _normal m00001>「……暗黒大樹の破壊だ。<stop_lip_animation n00133 CLOSE_MOUTH>",
    "ko": "<start_lip_sync n00133 _normal m00001>: ……암흑거목을 파괴하는 것뿐이다.<stop_lip_animation n00133 CLOSE_MOUTH>",
    "zh-hans": "<start_lip_sync n00133 _normal m00001>……破坏黑暗大树。<stop_lip_animation n00133 CLOSE_MOUTH>",
    "zh-hant": "<start_lip_sync n00133 _normal m00001>……破壞黑暗大樹。<stop_lip_animation n00133 CLOSE_MOUTH>"
  },
  "18536": {
    "de": "",
    "en": "",
    "es": "",
    "fr": "",
    "it": "",
    "ja": "<start_lip_sync m50042 _normal m00001>「……………。<stop_lip_animation m50042 CLOSE_MOUTH>",
    "ko": "<start_lip_sync m50042 _normal m00001>: …………….<stop_lip_animation m50042 CLOSE_MOUTH>",
    "zh-hans": "<start_lip_sync m50042 _normal m00001>…………<stop_lip_animation m50042 CLOSE_MOUTH>",
    "zh-hant": "<start_lip_sync m50042 _normal m00001>………………<stop_lip_animation m50042 CLOSE_MOUTH>"
  },
  "18537": {
    "de": "",
    "en": "",
    "es": "",
    "fr": "",
    "it": "",
    "ja": "<start_lip_sync n00133 _normal m00001>「私の後方には　大勢の兵士が控えている。\n　号令をかければ　大挙して押し寄せるだろう。<stop_lip_animation n00133 CLOSE_MOUTH>",
    "ko": "<start_lip_sync n00133 _normal m00001>: 내 뒤에는 수많은 병사가 대기 중이다.\n　명령만 내리면 한꺼번에 들이닥치겠지.<stop_lip_animation n00133 CLOSE_MOUTH>",
    "zh-hans": "<start_lip_sync n00133 _normal m00001>在我身后，有无数士兵在待命。\n号令一出，就将大举压上。<stop_lip_animation n00133 CLOSE_MOUTH>",
    "zh-hant": "<start_lip_sync n00133 _normal m00001>在我身後，有眾多士兵待命。\n號令一出，就會大舉進攻。<stop_lip_animation n00133 CLOSE_MOUTH>"
  },
  "18538": {
    "de": "",
    "en": "",
    "es": "",
    "fr": "",
    "it": "",
    "ja": "<start_lip_sync n00133 _normal m00001>「……そうなれば　双方とも\n　大きな被害が出ることは　まぬがれん。\n　できれば　戦いは避けたいのだ。<stop_lip_animation n00133 CLOSE_MOUTH>",
    "ko": "<start_lip_sync n00133 _normal m00001>: ……그렇게 되면 양쪽 모두가\n　큰 피해를 입을 수밖에 없다.\n　가능하다면 싸움은 피하고 싶다.<stop_lip_animation n00133 CLOSE_MOUTH>",
    "zh-hans": "<start_lip_sync n00133 _normal m00001>……如此一来，\n生灵涂炭在所难免。\n若有可能，我希望避免开启战端。<stop_lip_animation n00133 CLOSE_MOUTH>",
    "zh-hant": "<start_lip_sync n00133 _normal m00001>……如此一來，\n生靈塗炭在所難免。\n若有可能，我希望避免開啟戰端。<stop_lip_animation n00133 CLOSE_MOUTH>"
  },
  "18539": {
    "de": "",
    "en": "",
    "es": "",
    "fr": "",
    "it": "",
    "ja": "<start_lip_sync n00133 _normal m00001>「どうだ？\n　ムダな血を流す前に　退いてもらえぬか？<stop_lip_animation n00133 CLOSE_MOUTH>",
    "ko": "<start_lip_sync n00133 _normal m00001>: 어떤가?\n　불필요한 유혈 사태 전에 물러서 줄 순 없겠나?<stop_lip_animation n00133 CLOSE_MOUTH>",
    "zh-hans": "<start_lip_sync n00133 _normal m00001>可否让出一条路来，避免流血？\n尊驾意下如何？<stop_lip_animation n00133 CLOSE_MOUTH>",
    "zh-hant": "<start_lip_sync n00133 _normal m00001>如何？\n在釀成無謂的流血紛爭前，可否請尊駕退開？<stop_lip_animation n00133 CLOSE_MOUTH>"
  },
  "18540": {
    "de": "",
    "en": "",
    "es": "",
    "fr": "",
    "it": "",
    "ja": "<start_lip_sync m50042 _normal m00001>「お前　なにも　わかってない。<stop_lip_animation m50042 CLOSE_MOUTH>",
    "ko": "<start_lip_sync m50042 _normal m00001>: 너 아무것도 모른다.<stop_lip_animation m50042 CLOSE_MOUTH>",
    "zh-hans": "<start_lip_sync m50042 _normal m00001>你什么都不知道。<stop_lip_animation m50042 CLOSE_MOUTH>",
    "zh-hant": "<start_lip_sync m50042 _normal m00001>你什麼都不懂。<stop_lip_animation m50042 CLOSE_MOUTH>"
  },
  "18541": {
    "de": "",
    "en": "",
    "es": "",
    "fr": "",
    "it": "",
    "ja": "<start_lip_sync m50042 _normal m00001>「お前　なにも　見えてない。<stop_lip_animation m50042 CLOSE_MOUTH>",
    "ko": "<start_lip_sync m50042 _normal m00001>: 너 아무것도 보이지 않는다.<stop_lip_animation m50042 CLOSE_MOUTH>",
    "zh-hans": "<start_lip_sync m50042 _normal m00001>你什么都看不到。<stop_lip_animation m50042 CLOSE_MOUTH>",
    "zh-hant": "<start_lip_sync m50042 _normal m00001>什麼都看不到。<stop_lip_animation m50042 CLOSE_MOUTH>"
  },
  "18542": {
    "de": "",
    "en": "",
    "es": "",
    "fr": "",
    "it": "",
    "ja": "<start_lip_sync m50042 _normal m00001>「大樹の破壊\n　お前たちの寿命を　縮めるだけ。<stop_lip_animation m50042 CLOSE_MOUTH>",
    "ko": "<start_lip_sync m50042 _normal m00001>: 거목 파괴\n　너희 수명만 줄어든다.<stop_lip_animation m50042 CLOSE_MOUTH>",
    "zh-hans": "<start_lip_sync m50042 _normal m00001>破坏大树，\n只会缩短你们的寿命。<stop_lip_animation m50042 CLOSE_MOUTH>",
    "zh-hant": "<start_lip_sync m50042 _normal m00001>破壞大樹，\n只會縮短你們的壽命。<stop_lip_animation m50042 CLOSE_MOUTH>"
  },
  "18543": {
    "de": "",
    "en": "",
    "es": "",
    "fr": "",
    "it": "",
    "ja": "<start_lip_sync n00133 _normal m00001>「我々の寿命を　縮めるだと……？\n　いったい　どういうことだ？<stop_lip_animation n00133 CLOSE_MOUTH>",
    "ko": "<start_lip_sync n00133 _normal m00001>: 우리의 수명이 줄어든다고……?\n　대체 무슨 소리지?<stop_lip_animation n00133 CLOSE_MOUTH>",
    "zh-hans": "<start_lip_sync n00133 _normal m00001>缩短我们的寿命……吗？\n此乃何意？<stop_lip_animation n00133 CLOSE_MOUTH>",
    "zh-hant": "<start_lip_sync n00133 _normal m00001>縮短我們的壽命……？\n這到底是什麼意思？<stop_lip_animation n00133 CLOSE_MOUTH>"
  },
  "18544": {
    "de": "",
    "en": "",
    "es": "",
    "fr": "",
    "it": "",
    "ja": "<start_lip_sync m50042 _normal m00001>「ムリだ。言っても　わからない。\n　お前たち　見たものしか信じない。<stop_lip_animation m50042 CLOSE_MOUTH>",
    "ko": "<start_lip_sync m50042 _normal m00001>: 안 돼. 말해도 몰라.\n　너희 본 것만 믿는다.<stop_lip_animation m50042 CLOSE_MOUTH>",
    "zh-hans": "<start_lip_sync m50042 _normal m00001>告诉你也没用。你不会明白的。\n你们只会相信看到的东西。<stop_lip_animation m50042 CLOSE_MOUTH>",
    "zh-hant": "<start_lip_sync m50042 _normal m00001>說了也沒用，你們不會明白。\n你們只相信眼前看到的事物。<stop_lip_animation m50042 CLOSE_MOUTH>"
  },
  "18545": {
    "de": "",
    "en": "",
    "es": "",
    "fr": "",
    "it": "",
    "ja": "<start_lip_sync n00133 _normal m00001>「……そうか。\n　残念だが　交渉の余地は　なさそうだな。<stop_lip_animation n00133 CLOSE_MOUTH>",
    "ko": "<start_lip_sync n00133 _normal m00001>: ……알겠네.\n　안타깝지만 교섭의 여지는 없어 보이는군.<stop_lip_animation n00133 CLOSE_MOUTH>",
    "zh-hans": "<start_lip_sync n00133 _normal m00001>……是吗。\n太遗憾了，看来没有什么交涉的余地了啊。<stop_lip_animation n00133 CLOSE_MOUTH>",
    "zh-hant": "<start_lip_sync n00133 _normal m00001>……是嗎？\n太遺憾了，看來似乎沒什麼交涉的餘地。<stop_lip_animation n00133 CLOSE_MOUTH>"
  },
  "18546": {
    "de": "",
    "en": "",
    "es": "",
    "fr": "",
    "it": "",
    "ja": "<start_lip_sync n00133 _normal m00001>「許せ！！　暗黒大樹の番人たちよ！！<stop_lip_animation n00133 CLOSE_MOUTH>",
    "ko": "<start_lip_sync n00133 _normal m00001>: 용서하게!! 암흑거목의 파수꾼들이여!!<stop_lip_animation n00133 CLOSE_MOUTH>",
    "zh-hans": "<start_lip_sync n00133 _normal m00001>请原谅！！黑暗大树的看守们啊！！<stop_lip_animation n00133 CLOSE_MOUTH>",
    "zh-hant": "<start_lip_sync n00133 _normal m00001>原諒我吧！！黑暗大樹的看守們！！<stop_lip_animation n00133 CLOSE_MOUTH>"
  },
  "18547": {
    "de": "",
    "en": "",
    "es": "",
    "fr": "",
    "it": "",
    "ja": "<start_lip_sync n00133 _normal m00001>「全軍……！<stop_lip_animation n00133 CLOSE_MOUTH>",
    "ko": "<start_lip_sync n00133 _normal m00001>: 전군……!<stop_lip_animation n00133 CLOSE_MOUTH>",
    "zh-hans": "<start_lip_sync n00133 _normal m00001>全军……<stop_lip_animation n00133 CLOSE_MOUTH>",
    "zh-hant": "<start_lip_sync n00133 _normal m00001>全軍……！<stop_lip_animation n00133 CLOSE_MOUTH>"
  },
  "18548": {
    "de": "",
    "en": "",
    "es": "",
    "fr": "",
    "it": "",
    "ja": "<start_lip_sync n01419 _normal m00001>「震動……！？　地面から！？\n　ま…まずい！！<stop_lip_animation n01419 CLOSE_MOUTH>",
    "ko": "<start_lip_sync n01419 _normal m00001>: 진동……!? 지면에서!?\n　크… 큰일이야!!<stop_lip_animation n01419 CLOSE_MOUTH>",
    "zh-hans": "<start_lip_sync n01419 _normal m00001>震动？！从地面传来的？！\n糟……糟了！！<stop_lip_animation n01419 CLOSE_MOUTH>",
    "zh-hant": "<start_lip_sync n01419 _normal m00001>震動……！？從地面傳來的！？\n糟……糟了！！<stop_lip_animation n01419 CLOSE_MOUTH>"
  },
  "18549": {
    "de": "",
    "en": "",
    "es": "",
    "fr": "",
    "it": "",
    "ja": "<start_lip_sync n01419 _normal m00001>「王さま　危険です！\n　早く　この場から離れてください！<stop_lip_animation n01419 CLOSE_MOUTH>",
    "ko": "<start_lip_sync n01419 _normal m00001>: 왕이시여, 위험합니다!\n　어서 이곳에서 벗어나세요!<stop_lip_animation n01419 CLOSE_MOUTH>",
    "zh-hans": "<start_lip_sync n01419 _normal m00001>国王陛下，这里危险！\n请快点离开！<stop_lip_animation n01419 CLOSE_MOUTH>",
    "zh-hant": "<start_lip_sync n01419 _normal m00001>國王，這裡危險！\n請快點離開這裡！<stop_lip_animation n01419 CLOSE_MOUTH>"
  },
  "18550": {
    "de": "",
    "en": "",
    "es": "",
    "fr": "",
    "it": "",
    "ja": "<start_lip_sync n00133 _normal m00001>「な…なんだ！？<stop_lip_animation n00133 CLOSE_MOUTH>",
    "ko": "<start_lip_sync n00133 _normal m00001>: 뭐… 뭐라고!?<stop_lip_animation n00133 CLOSE_MOUTH>",
    "zh-hans": "<start_lip_sync n00133 _normal m00001>怎……怎么了？！<stop_lip_animation n00133 CLOSE_MOUTH>",
    "zh-hant": "<start_lip_sync n00133 _normal m00001>怎……怎麼回事！？<stop_lip_animation n00133 CLOSE_MOUTH>"
  },
  "18551": {
    "de": "",
    "en": "",
    "es": "",
    "fr": "",
    "it": "",
    "ja": "<start_lip_sync n00945 _normal m00001>「うん？　地面が……。<stop_lip_animation n00945 CLOSE_MOUTH>",
    "ko": "<start_lip_sync n00945 _normal m00001>: 응? 지면이…….<stop_lip_animation n00945 CLOSE_MOUTH>",
    "zh-hans": "<start_lip_sync n00945 _normal m00001>嗯？地面……<stop_lip_animation n00945 CLOSE_MOUTH>",
    "zh-hant": "<start_lip_sync n00945 _normal m00001>嗯？地面……<stop_lip_animation n00945 CLOSE_MOUTH>"
  },
  "18552": {
    "de": "",
    "en": "",
    "es": "",
    "fr": "",
    "it": "",
    "ja": "<start_lip_sync n00945 _normal m00001>「う…うわあああああーーーーー！！！<stop_lip_animation n00945 CLOSE_MOUTH>",
    "ko": "<start_lip_sync n00945 _normal m00001>: 으… 으아아아아아악!!!<stop_lip_animation n00945 CLOSE_MOUTH>",
    "zh-hans": "<start_lip_sync n00945 _normal m00001>呜……呜哇啊啊啊啊啊啊啊啊啊啊！！！<stop_lip_animation n00945 CLOSE_MOUTH>",
    "zh-hant": "<start_lip_sync n00945 _normal m00001>唔……唔哇啊啊啊啊啊──────！！！<stop_lip_animation n00945 CLOSE_MOUTH>"
  },
  "18553": {
    "de": "",
    "en": "",
    "es": "",
    "fr": "",
    "it": "",
    "ja": "<start_lip_sync n00133 _normal m00001>「魔瘴だと！？<stop_lip_animation n00133 CLOSE_MOUTH>",
    "ko": "<start_lip_sync n00133 _normal m00001>: 마장이!?<stop_lip_animation n00133 CLOSE_MOUTH>",
    "zh-hans": "<start_lip_sync n00133 _normal m00001>魔瘴？！<stop_lip_animation n00133 CLOSE_MOUTH>",
    "zh-hant": "<start_lip_sync n00133 _normal m00001>魔瘴！？<stop_lip_animation n00133 CLOSE_MOUTH>"
  },
  "18554": {
    "de": "",
    "en": "",
    "es": "",
    "fr": "",
    "it": "",
    "ja": "<start_lip_sync m50021 _normal m00001>「ギョギョ！　ギョギョギョ！<stop_lip_animation m50021 CLOSE_MOUTH>",
    "ko": "<start_lip_sync m50021 _normal m00001>: 키익키익! 키익키익키익!<stop_lip_animation m50021 CLOSE_MOUTH>",
    "zh-hans": "<start_lip_sync m50021 _normal m00001>啾啾！啾啾啾！<stop_lip_animation m50021 CLOSE_MOUTH>",
    "zh-hant": "<start_lip_sync m50021 _normal m00001>啾啾！啾啾啾！<stop_lip_animation m50021 CLOSE_MOUTH>"
  },
  "18555": {
    "de": "",
    "en": "",
    "es": "",
    "fr": "",
    "it": "",
    "ja": "<start_lip_sync n01419 _normal m00001>「しくじったわ……。逃げおくれた……。<stop_lip_animation n01419 CLOSE_MOUTH>",
    "ko": "<start_lip_sync n01419 _normal m00001>: 이런……. 도망칠 타이밍을 놓쳤군…….<stop_lip_animation n01419 CLOSE_MOUTH>",
    "zh-hans": "<start_lip_sync n01419 _normal m00001>这下惨啦……逃不掉了吗……<stop_lip_animation n01419 CLOSE_MOUTH>",
    "zh-hant": "<start_lip_sync n01419 _normal m00001>這下糟了……來不及逃走……<stop_lip_animation n01419 CLOSE_MOUTH>"
  },
  "18556": {
    "de": "",
    "en": "",
    "es": "",
    "fr": "",
    "it": "",
    "ja": "<start_lip_sync n01418 _normal m00001>「は…博士さん！！<stop_lip_animation n01418 CLOSE_MOUTH>",
    "ko": "<start_lip_sync n01418 _normal m00001>: 바… 박사님!!<stop_lip_animation n01418 CLOSE_MOUTH>",
    "zh-hans": "<start_lip_sync n01418 _normal m00001>博……博士姐姐！！<stop_lip_animation n01418 CLOSE_MOUTH>",
    "zh-hant": "<start_lip_sync n01418 _normal m00001>博……博士姊姊！！<stop_lip_animation n01418 CLOSE_MOUTH>"
  },
  "18557": {
    "de": "",
    "en": "",
    "es": "",
    "fr": "",
    "it": "",
    "ja": "<start_lip_sync n01419 _normal m00001>「ハッパ！？<stop_lip_animation n01419 CLOSE_MOUTH>",
    "ko": "<start_lip_sync n01419 _normal m00001>: 합파!?<stop_lip_animation n01419 CLOSE_MOUTH>",
    "zh-hans": "<start_lip_sync n01419 _normal m00001>叶？！<stop_lip_animation n01419 CLOSE_MOUTH>",
    "zh-hant": "<start_lip_sync n01419 _normal m00001>阿葉！？<stop_lip_animation n01419 CLOSE_MOUTH>"
  },
  "18558": {
    "de": "",
    "en": "",
    "es": "",
    "fr": "",
    "it": "",
    "ja": "<start_lip_sync n01418 _normal m00001>「ねえ！　博士さんを助けにいこう！<stop_lip_animation n01418 CLOSE_MOUTH>",
    "ko": "<start_lip_sync n01418 _normal m00001>: 우리가 가서 박사님을 구해 주자!<stop_lip_animation n01418 CLOSE_MOUTH>",
    "zh-hans": "<start_lip_sync n01418 _normal m00001>快！去救博士姐姐吧！<stop_lip_animation n01418 CLOSE_MOUTH>",
    "zh-hant": "<start_lip_sync n01418 _normal m00001>快！我們去救博士姊姊吧！<stop_lip_animation n01418 CLOSE_MOUTH>"
  },
  "18559": {
    "de": "",
    "en": "",
    "es": "",
    "fr": "",
    "it": "",
    "ja": "<start_lip_sync n01418 _normal m00001>「博士さんたちが　あぶない！<stop_lip_animation n01418 CLOSE_MOUTH>",
    "ko": "<start_lip_sync n01418 _normal m00001>: 박사님 쪽이 위험해!<stop_lip_animation n01418 CLOSE_MOUTH>",
    "zh-hans": "<start_lip_sync n01418 _normal m00001>博士姐姐危险了！<stop_lip_animation n01418 CLOSE_MOUTH>",
    "zh-hant": "<start_lip_sync n01418 _normal m00001>博士姊姊他們危險了！<stop_lip_animation n01418 CLOSE_MOUTH>"
  },
  "18560": {
    "de": "",
    "en": "",
    "es": "",
    "fr": "",
    "it": "",
    "ja": "<start_lip_sync n01418 _normal m00001>「ねえ！　みんなを助けにいこう！<stop_lip_animation n01418 CLOSE_MOUTH>",
    "ko": "<start_lip_sync n01418 _normal m00001>: 우리가 가서 모두 구해 주자!<stop_lip_animation n01418 CLOSE_MOUTH>",
    "zh-hans": "<start_lip_sync n01418 _normal m00001>求求你！救救大家吧！<stop_lip_animation n01418 CLOSE_MOUTH>",
    "zh-hant": "<start_lip_sync n01418 _normal m00001>拜託了！去救大家吧！<stop_lip_animation n01418 CLOSE_MOUTH>"
  },
  "18561": {
    "de": "",
    "en": "",
    "es": "",
    "fr": "",
    "it": "",
    "ja": "<start_lip_sync m50042 _normal m00001>「ましょううおを　倒したか。\n　お前　勇気ある者だ。<stop_lip_animation m50042 CLOSE_MOUTH>",
    "ko": "<start_lip_sync m50042 _normal m00001>: 마장어를 쓰러뜨렸군.\n　너 용기 있는 자다.<stop_lip_animation m50042 CLOSE_MOUTH>",
    "zh-hans": "<start_lip_sync m50042 _normal m00001>打倒了魔瘴鱼啊。\n你真是个勇敢的人。<stop_lip_animation m50042 CLOSE_MOUTH>",
    "zh-hant": "<start_lip_sync m50042 _normal m00001>打倒魔瘴魚了嗎？\n你真是個勇敢的人。<stop_lip_animation m50042 CLOSE_MOUTH>"
  },
  "18562": {
    "de": "",
    "en": "",
    "es": "",
    "fr": "",
    "it": "",
    "ja": "<start_lip_sync m50042 _normal m00001>「ハッパ。強い仲間　持ったな。<stop_lip_animation m50042 CLOSE_MOUTH>",
    "ko": "<start_lip_sync m50042 _normal m00001>: 합파. 강한 동료 가졌구나.<stop_lip_animation m50042 CLOSE_MOUTH>",
    "zh-hans": "<start_lip_sync m50042 _normal m00001>叶。你有了强大的伙伴啊。<stop_lip_animation m50042 CLOSE_MOUTH>",
    "zh-hant": "<start_lip_sync m50042 _normal m00001>阿葉，你有了強大的夥伴呢。<stop_lip_animation m50042 CLOSE_MOUTH>"
  },
  "18563": {
    "de": "",
    "en": "",
    "es": "",
    "fr": "",
    "it": "",
    "ja": "<start_lip_sync n01418 _normal m00001>「パパ……。<stop_lip_animation n01418 CLOSE_MOUTH>",
    "ko": "<start_lip_sync n01418 _normal m00001>: 아빠…….<stop_lip_animation n01418 CLOSE_MOUTH>",
    "zh-hans": "<start_lip_sync n01418 _normal m00001>……爸爸？<stop_lip_animation n01418 CLOSE_MOUTH>",
    "zh-hant": "<start_lip_sync n01418 _normal m00001>爸爸……<stop_lip_animation n01418 CLOSE_MOUTH>"
  },
  "18564": {
    "de": "",
    "en": "",
    "es": "",
    "fr": "",
    "it": "",
    "ja": "<start_lip_sync n01419 _normal m00001>「パパ……？\n　暗黒大樹の長が　育ての親だったのね……。<stop_lip_animation n01419 CLOSE_MOUTH>",
    "ko": "<start_lip_sync n01419 _normal m00001>: 아빠……?\n　암흑거목 대장이 널 길러 준 거였구나…….<stop_lip_animation n01419 CLOSE_MOUTH>",
    "zh-hans": "<start_lip_sync n01419 _normal m00001>爸爸……吗？\n原来黑暗大树之长就是他的养父啊……<stop_lip_animation n01419 CLOSE_MOUTH>",
    "zh-hant": "<start_lip_sync n01419 _normal m00001>爸爸……？\n原來黑暗大樹的長老就是他的養父啊……<stop_lip_animation n01419 CLOSE_MOUTH>"
  },
  "18565": {
    "de": "",
    "en": "",
    "es": "",
    "fr": "",
    "it": "",
    "ja": "<start_lip_sync n00133 _normal m00001>「な…なんだ　今のは！？<stop_lip_animation n00133 CLOSE_MOUTH>",
    "ko": "<start_lip_sync n00133 _normal m00001>: 바… 방금 그건 뭐지!?<stop_lip_animation n00133 CLOSE_MOUTH>",
    "zh-hans": "<start_lip_sync n00133 _normal m00001>刚……刚刚那是怎么回事？！<stop_lip_animation n00133 CLOSE_MOUTH>",
    "zh-hant": "<start_lip_sync n00133 _normal m00001>剛……剛才那是怎麼回事！？<stop_lip_animation n00133 CLOSE_MOUTH>"
  },
  "18566": {
    "de": "",
    "en": "",
    "es": "",
    "fr": "",
    "it": "",
    "ja": "<start_lip_sync n00133 _normal m00001>「暗黒大樹が光り\n　魔瘴を　取り込んでいった！？<stop_lip_animation n00133 CLOSE_MOUTH>",
    "ko": "<start_lip_sync n00133 _normal m00001>: 암흑거목이 빛을 내며\n　마장을 빨아들이다니!?<stop_lip_animation n00133 CLOSE_MOUTH>",
    "zh-hans": "<start_lip_sync n00133 _normal m00001>黑暗大树在发光，\n把魔瘴吸进去了？！<stop_lip_animation n00133 CLOSE_MOUTH>",
    "zh-hant": "<start_lip_sync n00133 _normal m00001>黑暗大樹發光，\n把魔瘴吸進去了！？<stop_lip_animation n00133 CLOSE_MOUTH>"
  },
  "18567": {
    "de": "",
    "en": "",
    "es": "",
    "fr": "",
    "it": "",
    "ja": "<start_lip_sync n01419 _normal m00001>「暗黒…大樹が……？<stop_lip_animation n01419 CLOSE_MOUTH>",
    "ko": "<start_lip_sync n01419 _normal m00001>: 암흑…거목이……?<stop_lip_animation n01419 CLOSE_MOUTH>",
    "zh-hans": "<start_lip_sync n01419 _normal m00001>黑暗……大树……吗？<stop_lip_animation n01419 CLOSE_MOUTH>",
    "zh-hant": "<start_lip_sync n01419 _normal m00001>黑暗……大樹……？<stop_lip_animation n01419 CLOSE_MOUTH>"
  },
  "18568": {
    "de": "",
    "en": "",
    "es": "",
    "fr": "",
    "it": "",
    "ja": "<start_lip_sync n01419 _normal m00001>「そういうことだったのか……。<stop_lip_animation n01419 CLOSE_MOUTH>",
    "ko": "<start_lip_sync n01419 _normal m00001>: 그런 거였구나…….<stop_lip_animation n01419 CLOSE_MOUTH>",
    "zh-hans": "<start_lip_sync n01419 _normal m00001>原来是这么回事啊……<stop_lip_animation n01419 CLOSE_MOUTH>",
    "zh-hant": "<start_lip_sync n01419 _normal m00001>原來是這麼回事……<stop_lip_animation n01419 CLOSE_MOUTH>"
  },
  "18569": {
    "de": "",
    "en": "",
    "es": "",
    "fr": "",
    "it": "",
    "ja": "<start_lip_sync n01419 _normal m00001>「ふふっ。まいった……。\n　これは　想像以上の発見だわ。<stop_lip_animation n01419 CLOSE_MOUTH>",
    "ko": "<start_lip_sync n01419 _normal m00001>: 후훗. 놀라워…….\n　이건 상상을 뛰어넘는 발견이야.<stop_lip_animation n01419 CLOSE_MOUTH>",
    "zh-hans": "<start_lip_sync n01419 _normal m00001>呵呵。我服啦……\n这可真是意外的发现呢。<stop_lip_animation n01419 CLOSE_MOUTH>",
    "zh-hant": "<start_lip_sync n01419 _normal m00001>呵呵，真是的……\n這可是超乎想像的發現呢。<stop_lip_animation n01419 CLOSE_MOUTH>"
  },
  "18570": {
    "de": "",
    "en": "",
    "es": "",
    "fr": "",
    "it": "",
    "ja": "<start_lip_sync n01419 _normal m00001>「この樹は　魔瘴を取り込み　浄化することで\n　魔瘴から　エルトナ大陸を守ってきたのね。<stop_lip_animation n01419 CLOSE_MOUTH>",
    "ko": "<start_lip_sync n01419 _normal m00001>: 이 나무는 마장을 흡수하고 정화해서\n　마장으로부터 엘토나 대륙을 지키고 있었구나.<stop_lip_animation n01419 CLOSE_MOUTH>",
    "zh-hans": "<start_lip_sync n01419 _normal m00001>吸收魔瘴并加以净化，守护埃尔托纳大陆\n不被魔瘴侵害的正是这棵树啊。<stop_lip_animation n01419 CLOSE_MOUTH>",
    "zh-hant": "<start_lip_sync n01419 _normal m00001>這棵樹藉由吸收魔瘴並加以淨化的方式，\n一直以來保護著艾爾托納大陸不受魔瘴侵害對吧。<stop_lip_animation n01419 CLOSE_MOUTH>"
  },
  "18571": {
    "de": "",
    "en": "",
    "es": "",
    "fr": "",
    "it": "",
    "ja": "<start_lip_sync n00133 _normal m00001>「な…なんだと！？<stop_lip_animation n00133 CLOSE_MOUTH>",
    "ko": "<start_lip_sync n00133 _normal m00001>: 뭐… 뭐라고!?<stop_lip_animation n00133 CLOSE_MOUTH>",
    "zh-hans": "<start_lip_sync n00133 _normal m00001>你、你说什么？！<stop_lip_animation n00133 CLOSE_MOUTH>",
    "zh-hant": "<start_lip_sync n00133 _normal m00001>妳……妳說什麼！？<stop_lip_animation n00133 CLOSE_MOUTH>"
  },
  "18572": {
    "de": "",
    "en": "",
    "es": "",
    "fr": "",
    "it": "",
    "ja": "<start_lip_sync m50042 _normal m00001>「そうだ。お前　賢い者だ。<stop_lip_animation m50042 CLOSE_MOUTH>",
    "ko": "<start_lip_sync m50042 _normal m00001>: 그렇다. 너 현명한 자다.<stop_lip_animation m50042 CLOSE_MOUTH>",
    "zh-hans": "<start_lip_sync m50042 _normal m00001>不错。你很聪明。<stop_lip_animation m50042 CLOSE_MOUTH>",
    "zh-hant": "<start_lip_sync m50042 _normal m00001>沒錯，妳是個聰明人。<stop_lip_animation m50042 CLOSE_MOUTH>"
  },
  "18573": {
    "de": "",
    "en": "",
    "es": "",
    "fr": "",
    "it": "",
    "ja": "<start_lip_sync m50042 _normal m00001>「エルトナ大陸に発生した　魔瘴。\n　聖なる大樹　魔瘴を取り込んでいき\n　どんどん　黒く染まっていった。<stop_lip_animation m50042 CLOSE_MOUTH>",
    "ko": "<start_lip_sync m50042 _normal m00001>: 엘토나 대륙에 발생한 마장.\n　신성한 거목 마장 빨아들여서\n　점점 검게 물들어 갔다.<stop_lip_animation m50042 CLOSE_MOUTH>",
    "zh-hans": "<start_lip_sync m50042 _normal m00001>神圣大树不断吸收着\n埃尔托纳大陆上产生的魔瘴，\n慢慢地就被染成了黑色。<stop_lip_animation m50042 CLOSE_MOUTH>",
    "zh-hant": "<start_lip_sync m50042 _normal m00001>神聖大樹不斷吸收著\n艾爾托納大陸上產生的魔瘴，\n慢慢地就被染成了黑色。<stop_lip_animation m50042 CLOSE_MOUTH>"
  },
  "18574": {
    "de": "",
    "en": "",
    "es": "",
    "fr": "",
    "it": "",
    "ja": "<start_lip_sync m50042 _normal m00001>「なにも知らない　エルフたち。\n　いつからか　聖なる大樹を\n　暗黒大樹と呼ぶようになった。<stop_lip_animation m50042 CLOSE_MOUTH>",
    "ko": "<start_lip_sync m50042 _normal m00001>: 아무것도 모르는 엘프들.\n　언제부턴가 신성한 거목을\n　암흑거목이라 불렀다.<stop_lip_animation m50042 CLOSE_MOUTH>",
    "zh-hans": "<start_lip_sync m50042 _normal m00001>无知的埃尔夫们\n不知从何时起，\n开始将神圣大树称为黑暗大树。<stop_lip_animation m50042 CLOSE_MOUTH>",
    "zh-hant": "<start_lip_sync m50042 _normal m00001>不知從何時起，\n無知的艾爾芙們便開始\n將神聖大樹稱為黑暗大樹。<stop_lip_animation m50042 CLOSE_MOUTH>"
  },
  "18575": {
    "de": "",
    "en": "",
    "es": "",
    "fr": "",
    "it": "",
    "ja": "<start_lip_sync n01419 _normal m00001>「だけど長年　魔瘴を取り込んだせいで\n　この樹の　はたらきは　徐々に弱まっていった。\n　次第に　魔瘴を取り込むチカラは落ちていき……<stop_lip_animation n01419 CLOSE_MOUTH>",
    "ko": "<start_lip_sync n01419 _normal m00001>: 하지만 오랜 세월, 마장을 흡수한 탓에\n　이 나무의 효과는 서서히 약해졌겠지.\n　점차 마장을 흡수하는 힘은 떨어지고……<stop_lip_animation n01419 CLOSE_MOUTH>",
    "zh-hans": "<start_lip_sync n01419 _normal m00001>随着常年吸收魔瘴，\n这棵树的活力也慢慢变弱了。\n吸收魔瘴的力量不断下降……<stop_lip_animation n01419 CLOSE_MOUTH>",
    "zh-hant": "<start_lip_sync n01419 _normal m00001>但是隨著長年吸收魔瘴，\n這棵樹的效用也逐漸變弱。\n吸收魔瘴的力量持續衰退……<stop_lip_animation n01419 CLOSE_MOUTH>"
  },
  "18576": {
    "de": "",
    "en": "",
    "es": "",
    "fr": "",
    "it": "",
    "ja": "<start_lip_sync n01419 _normal m00001>「取り込みきれず　あふれた魔瘴が\n　今　各地で　ふきだしている。\n　暗黒大樹の正体は……<stop_lip_animation n01419 CLOSE_MOUTH>",
    "ko": "<start_lip_sync n01419 _normal m00001>: 미처 빨아들이지 못한 마장이\n　지금 각지에서 분출되고 있는 거야.\n　암흑거목의 정체는……<stop_lip_animation n01419 CLOSE_MOUTH>",
    "zh-hans": "<start_lip_sync n01419 _normal m00001>现在，无法被吸收掉的魔瘴，\n就在各地涌现出来。\n黑暗大树的真面目其实……<stop_lip_animation n01419 CLOSE_MOUTH>",
    "zh-hant": "<start_lip_sync n01419 _normal m00001>無法吸收的魔瘴\n如今在各地湧出。\n黑暗大樹的真面目……<stop_lip_animation n01419 CLOSE_MOUTH>"
  },
  "18577": {
    "de": "",
    "en": "",
    "es": "",
    "fr": "",
    "it": "",
    "ja": "<start_lip_sync n01419 _normal m00001>「すなわち　世界樹。そういうことね？<stop_lip_animation n01419 CLOSE_MOUTH>",
    "ko": "<start_lip_sync n01419 _normal m00001>: 다시 말해 세계수. 내 말이 맞지?<stop_lip_animation n01419 CLOSE_MOUTH>",
    "zh-hans": "<start_lip_sync n01419 _normal m00001>其实就是世界树。没错吧？<stop_lip_animation n01419 CLOSE_MOUTH>",
    "zh-hant": "<start_lip_sync n01419 _normal m00001>其實就是世界樹，對吧？<stop_lip_animation n01419 CLOSE_MOUTH>"
  },
  "18578": {
    "de": "",
    "en": "",
    "es": "",
    "fr": "",
    "it": "",
    "ja": "<start_lip_sync m50042 _normal m00001>「そうだ。<stop_lip_animation m50042 CLOSE_MOUTH>",
    "ko": "<start_lip_sync m50042 _normal m00001>: 그렇다.<stop_lip_animation m50042 CLOSE_MOUTH>",
    "zh-hans": "<start_lip_sync m50042 _normal m00001>是。<stop_lip_animation m50042 CLOSE_MOUTH>",
    "zh-hant": "<start_lip_sync m50042 _normal m00001>沒錯。<stop_lip_animation m50042 CLOSE_MOUTH>"
  },
  "18579": {
    "de": "",
    "en": "",
    "es": "",
    "fr": "",
    "it": "",
    "ja": "<start_lip_sync n00133 _normal m00001>「な…なんだと！？\n　この暗黒大樹が　大いなる緑の象徴！？<stop_lip_animation n00133 CLOSE_MOUTH>",
    "ko": "<start_lip_sync n00133 _normal m00001>: 뭐… 뭐라고!?\n　이 암흑거목이 위대한 초록빛의 상징!?<stop_lip_animation n00133 CLOSE_MOUTH>",
    "zh-hans": "<start_lip_sync n00133 _normal m00001>什……什么？！\n这黑暗大树其实是大自然的象征？！<stop_lip_animation n00133 CLOSE_MOUTH>",
    "zh-hant": "<start_lip_sync n00133 _normal m00001>什……什麼！？\n這棵黑暗大樹其實是大自然的象徵！？<stop_lip_animation n00133 CLOSE_MOUTH>"
  },
  "18580": {
    "de": "",
    "en": "",
    "es": "",
    "fr": "",
    "it": "",
    "ja": "<start_lip_sync n00133 _normal m00001>「はるか昔から　私たちエルフを\n　見守り続けてきた　世界樹だというのか……？<stop_lip_animation n00133 CLOSE_MOUTH>",
    "ko": "<start_lip_sync n00133 _normal m00001>: 까마득한 옛날부터 우리 엘프를\n　줄곧 지켜본 세계수란 말인가……?<stop_lip_animation n00133 CLOSE_MOUTH>",
    "zh-hans": "<start_lip_sync n00133 _normal m00001>就是从古至今，\n守护着我等埃尔夫的世界树……吗？<stop_lip_animation n00133 CLOSE_MOUTH>",
    "zh-hant": "<start_lip_sync n00133 _normal m00001>也就是從古至今，\n守護著我等艾爾芙的世界樹嗎……？<stop_lip_animation n00133 CLOSE_MOUTH>"
  },
  "18581": {
    "de": "",
    "en": "",
    "es": "",
    "fr": "",
    "it": "",
    "ja": "<start_lip_sync m50042 _normal m00001>「大樹の番人　大樹を見守るのが役目。\n　誰にも　ジャマさせない。<stop_lip_animation m50042 CLOSE_MOUTH>",
    "ko": "<start_lip_sync m50042 _normal m00001>: 거목의 파수꾼 거목을 지켜보는 역할.\n　아무도 방해할 수 없다.<stop_lip_animation m50042 CLOSE_MOUTH>",
    "zh-hans": "<start_lip_sync m50042 _normal m00001>我乃大树的看守，我的使命是守护大树。\n不会容忍任何人妨碍我。<stop_lip_animation m50042 CLOSE_MOUTH>",
    "zh-hant": "<start_lip_sync m50042 _normal m00001>我乃大樹看守，守護大樹是我的使命。\n絕不容許任何人妨礙。<stop_lip_animation m50042 CLOSE_MOUTH>"
  },
  "18582": {
    "de": "",
    "en": "",
    "es": "",
    "fr": "",
    "it": "",
    "ja": "<start_lip_sync m50042 _normal m00001>「エルフたちよ。去れ。<stop_lip_animation m50042 CLOSE_MOUTH>",
    "ko": "<start_lip_sync m50042 _normal m00001>: 엘프들이여. 가라.<stop_lip_animation m50042 CLOSE_MOUTH>",
    "zh-hans": "<start_lip_sync m50042 _normal m00001>埃尔夫们啊。离开吧。<stop_lip_animation m50042 CLOSE_MOUTH>",
    "zh-hant": "<start_lip_sync m50042 _normal m00001>艾爾芙們，離開吧。<stop_lip_animation m50042 CLOSE_MOUTH>"
  },
  "18583": {
    "de": "",
    "en": "",
    "es": "",
    "fr": "",
    "it": "",
    "ja": "<start_lip_sync n01418 _normal m00001>「パパ……？<stop_lip_animation n01418 CLOSE_MOUTH>",
    "ko": "<start_lip_sync n01418 _normal m00001>: 아빠……?<stop_lip_animation n01418 CLOSE_MOUTH>",
    "zh-hans": "<start_lip_sync n01418 _normal m00001>……爸爸？<stop_lip_animation n01418 CLOSE_MOUTH>",
    "zh-hant": "<start_lip_sync n01418 _normal m00001>爸爸……？<stop_lip_animation n01418 CLOSE_MOUTH>"
  },
  "18584": {
    "de": "",
    "en": "",
    "es": "",
    "fr": "",
    "it": "",
    "ja": "<start_lip_sync m50042 _normal m00001>「ハッパ　立派になった。<stop_lip_animation m50042 CLOSE_MOUTH>",
    "ko": "<start_lip_sync m50042 _normal m00001>: 합파 의젓해졌다.<stop_lip_animation m50042 CLOSE_MOUTH>",
    "zh-hans": "<start_lip_sync m50042 _normal m00001>叶，你长大了啊。<stop_lip_animation m50042 CLOSE_MOUTH>",
    "zh-hant": "<start_lip_sync m50042 _normal m00001>阿葉，你長大了啊。<stop_lip_animation m50042 CLOSE_MOUTH>"
  },
  "18585": {
    "de": "",
    "en": "",
    "es": "",
    "fr": "",
    "it": "",
    "ja": "<start_lip_sync n01418 _normal m00001>「うん……。\n　ボク　博士さんの所で\n　いっぱい　お手伝いしたから……。<stop_lip_animation n01418 CLOSE_MOUTH>",
    "ko": "<start_lip_sync n01418 _normal m00001>: 응…….\n　나 박사님 곁에서\n　많이많이 도왔어. 그래서…….<stop_lip_animation n01418 CLOSE_MOUTH>",
    "zh-hans": "<start_lip_sync n01418 _normal m00001>嗯……\n我在博士姐姐那里，\n帮着做了很多事……<stop_lip_animation n01418 CLOSE_MOUTH>",
    "zh-hant": "<start_lip_sync n01418 _normal m00001>嗯……\n我在博士姊姊那裡\n幫忙了很多事……<stop_lip_animation n01418 CLOSE_MOUTH>"
  },
  "18586": {
    "de": "",
    "en": "",
    "es": "",
    "fr": "",
    "it": "",
    "ja": "<start_lip_sync m50042 _normal m00001>「博士さん？<stop_lip_animation m50042 CLOSE_MOUTH>",
    "ko": "<start_lip_sync m50042 _normal m00001>: 박사님?<stop_lip_animation m50042 CLOSE_MOUTH>",
    "zh-hans": "<start_lip_sync m50042 _normal m00001>博士姐姐？<stop_lip_animation m50042 CLOSE_MOUTH>",
    "zh-hant": "<start_lip_sync m50042 _normal m00001>博士姊姊？<stop_lip_animation m50042 CLOSE_MOUTH>"
  },
  "18587": {
    "de": "",
    "en": "",
    "es": "",
    "fr": "",
    "it": "",
    "ja": "<start_lip_sync n01419 _normal m00001>「あたしのことよ。<stop_lip_animation n01419 CLOSE_MOUTH>",
    "ko": "<start_lip_sync n01419 _normal m00001>: 나를 말하는 거야.<stop_lip_animation n01419 CLOSE_MOUTH>",
    "zh-hans": "<start_lip_sync n01419 _normal m00001>就是我哦。<stop_lip_animation n01419 CLOSE_MOUTH>",
    "zh-hant": "<start_lip_sync n01419 _normal m00001>就是我。<stop_lip_animation n01419 CLOSE_MOUTH>"
  },
  "18588": {
    "de": "",
    "en": "",
    "es": "",
    "fr": "",
    "it": "",
    "ja": "<start_lip_sync m50042 _normal m00001>「賢い者か。\n　お前に　感謝する。<stop_lip_animation m50042 CLOSE_MOUTH>",
    "ko": "<start_lip_sync m50042 _normal m00001>: 현명한 자로군.\n　너에게 고맙다.<stop_lip_animation m50042 CLOSE_MOUTH>",
    "zh-hans": "<start_lip_sync m50042 _normal m00001>原来是聪明人。\n我要向你道谢。<stop_lip_animation m50042 CLOSE_MOUTH>",
    "zh-hant": "<start_lip_sync m50042 _normal m00001>原來是聰明人。\n我要向妳道謝。<stop_lip_animation m50042 CLOSE_MOUTH>"
  },
  "18589": {
    "de": "",
    "en": "",
    "es": "",
    "fr": "",
    "it": "",
    "ja": "<start_lip_sync m50042 _normal m00001>「……ハッパ。なぜ　お前を\n　ここから　追いだしたのか話す。<stop_lip_animation m50042 CLOSE_MOUTH>",
    "ko": "<start_lip_sync m50042 _normal m00001>: ……합파. 왜 널 여기서\n　쫓아냈는지 얘기한다.<stop_lip_animation m50042 CLOSE_MOUTH>",
    "zh-hans": "<start_lip_sync m50042 _normal m00001>……叶。\n我现在告诉你为何会把你赶走。<stop_lip_animation m50042 CLOSE_MOUTH>",
    "zh-hant": "<start_lip_sync m50042 _normal m00001>……阿葉，我現在就告訴你，\n為何會把你趕走。<stop_lip_animation m50042 CLOSE_MOUTH>"
  },
  "18590": {
    "de": "",
    "en": "",
    "es": "",
    "fr": "",
    "it": "",
    "ja": "<start_lip_sync m50042 _normal m00001>「大樹　芯まで　濃い魔瘴に覆われた。\n　芯　大樹の命。<stop_lip_animation m50042 CLOSE_MOUTH>",
    "ko": "<start_lip_sync m50042 _normal m00001>: 거목 중심까지 짙은 마장으로 뒤덮였다.\n　중심은 거목의 생명.<stop_lip_animation m50042 CLOSE_MOUTH>",
    "zh-hans": "<start_lip_sync m50042 _normal m00001>大树的树芯已经被浓重的魔瘴覆盖了。\n树芯是大树的命脉。<stop_lip_animation m50042 CLOSE_MOUTH>",
    "zh-hant": "<start_lip_sync m50042 _normal m00001>大樹的樹芯已經被濃厚的魔瘴覆蓋了。\n樹芯是大樹的命脈。<stop_lip_animation m50042 CLOSE_MOUTH>"
  },
  "18591": {
    "de": "",
    "en": "",
    "es": "",
    "fr": "",
    "it": "",
    "ja": "<start_lip_sync m50042 _normal m00001>「大樹　もうすぐ　限界。\n　魔瘴を　取り込めなくなる。<stop_lip_animation m50042 CLOSE_MOUTH>",
    "ko": "<start_lip_sync m50042 _normal m00001>: 거목 곧 한계다.\n　마장 빨아들일 수 없게 된다.<stop_lip_animation m50042 CLOSE_MOUTH>",
    "zh-hans": "<start_lip_sync m50042 _normal m00001>大树的承受能力就快到极限了。\n不能再吸收魔瘴了。<stop_lip_animation m50042 CLOSE_MOUTH>",
    "zh-hant": "<start_lip_sync m50042 _normal m00001>大樹就快到極限了。\n會無法再吸收魔瘴。<stop_lip_animation m50042 CLOSE_MOUTH>"
  },
  "18592": {
    "de": "",
    "en": "",
    "es": "",
    "fr": "",
    "it": "",
    "ja": "<start_lip_sync m50042 _normal m00001>「ここ　濃い魔瘴だらけになったら\n　エルフの　お前　生きていけなくなる。\n　だから　お前を遠ざけた。<stop_lip_animation m50042 CLOSE_MOUTH>",
    "ko": "<start_lip_sync m50042 _normal m00001>: 여기 짙은 마장투성이 되면\n　엘프인 너 살 수 없게 된다.\n　그래서 너를 멀리했다.<stop_lip_animation m50042 CLOSE_MOUTH>",
    "zh-hans": "<start_lip_sync m50042 _normal m00001>等这里充满浓重的魔瘴时，\n身为埃尔夫的你就会无法存活。\n所以我才疏远你。<stop_lip_animation m50042 CLOSE_MOUTH>",
    "zh-hant": "<start_lip_sync m50042 _normal m00001>等這裡充滿濃厚的魔瘴時，\n身為艾爾芙的你就會無法存活。\n所以我才讓你遠離這裡。<stop_lip_animation m50042 CLOSE_MOUTH>"
  },
  "18593": {
    "de": "",
    "en": "",
    "es": "",
    "fr": "",
    "it": "",
    "ja": "<start_lip_sync n01418 _normal m00001>「そ…そんな！\n　大樹を　助けられないの！？<stop_lip_animation n01418 CLOSE_MOUTH>",
    "ko": "<start_lip_sync n01418 _normal m00001>: 어… 어떡해!\n　거목을 도울 수는 없어!?<stop_lip_animation n01418 CLOSE_MOUTH>",
    "zh-hans": "<start_lip_sync n01418 _normal m00001>怎……怎么会这样！\n大树已经没救了吗？！<stop_lip_animation n01418 CLOSE_MOUTH>",
    "zh-hant": "<start_lip_sync n01418 _normal m00001>怎……怎麼會這樣！\n大樹已經沒救了嗎！？<stop_lip_animation n01418 CLOSE_MOUTH>"
  },
  "18594": {
    "de": "",
    "en": "",
    "es": "",
    "fr": "",
    "it": "",
    "ja": "<start_lip_sync m50042 _normal m00001>「これも　自然の意志。<stop_lip_animation m50042 CLOSE_MOUTH>",
    "ko": "<start_lip_sync m50042 _normal m00001>: 이 또한 자연의 의지.<stop_lip_animation m50042 CLOSE_MOUTH>",
    "zh-hans": "<start_lip_sync m50042 _normal m00001>这也是自然的意志。<stop_lip_animation m50042 CLOSE_MOUTH>",
    "zh-hant": "<start_lip_sync m50042 _normal m00001>這也是自然的意志。<stop_lip_animation m50042 CLOSE_MOUTH>"
  },
  "18595": {
    "de": "",
    "en": "",
    "es": "",
    "fr": "",
    "it": "",
    "ja": "<start_lip_sync m50042 _normal m00001>「さらばだ。<stop_lip_animation m50042 CLOSE_MOUTH>",
    "ko": "<start_lip_sync m50042 _normal m00001>: 잘 가라.<stop_lip_animation m50042 CLOSE_MOUTH>",
    "zh-hans": "<start_lip_sync m50042 _normal m00001>再见了。<stop_lip_animation m50042 CLOSE_MOUTH>",
    "zh-hant": "<start_lip_sync m50042 _normal m00001>再見了。<stop_lip_animation m50042 CLOSE_MOUTH>"
  },
  "18596": {
    "de": "",
    "en": "",
    "es": "",
    "fr": "",
    "it": "",
    "ja": "<start_lip_sync n01419 _normal m00001>「……対策を　練り直すべきね。<stop_lip_animation n01419 CLOSE_MOUTH>",
    "ko": "<start_lip_sync n01419 _normal m00001>: ……대책을 다시 세워야겠어.<stop_lip_animation n01419 CLOSE_MOUTH>",
    "zh-hans": "<start_lip_sync n01419 _normal m00001>……得重新研究对策了。<stop_lip_animation n01419 CLOSE_MOUTH>",
    "zh-hant": "<start_lip_sync n01419 _normal m00001>……得重新擬定對策了。<stop_lip_animation n01419 CLOSE_MOUTH>"
  },
  "18597": {
    "de": "",
    "en": "",
    "es": "",
    "fr": "",
    "it": "",
    "ja": "<start_lip_sync n01419 _normal m00001>「王さま。ひとまず　城に戻りましょう。<stop_lip_animation n01419 CLOSE_MOUTH>",
    "ko": "<start_lip_sync n01419 _normal m00001>: 왕이시여. 일단 성으로 돌아가시죠.<stop_lip_animation n01419 CLOSE_MOUTH>",
    "zh-hans": "<start_lip_sync n01419 _normal m00001>国王陛下。先回城吧。<stop_lip_animation n01419 CLOSE_MOUTH>",
    "zh-hant": "<start_lip_sync n01419 _normal m00001>國王，先回城吧。<stop_lip_animation n01419 CLOSE_MOUTH>"
  },
  "18598": {
    "de": "",
    "en": "",
    "es": "",
    "fr": "",
    "it": "",
    "ja": "<start_lip_sync n00133 _normal m00001>「うむ……。<stop_lip_animation n00133 CLOSE_MOUTH>",
    "ko": "<start_lip_sync n00133 _normal m00001>: 그래…….<stop_lip_animation n00133 CLOSE_MOUTH>",
    "zh-hans": "<start_lip_sync n00133 _normal m00001>嗯……<stop_lip_animation n00133 CLOSE_MOUTH>",
    "zh-hant": "<start_lip_sync n00133 _normal m00001>嗯……<stop_lip_animation n00133 CLOSE_MOUTH>"
  },
  "18599": {
    "de": "",
    "en": "",
    "es": "",
    "fr": "",
    "it": "",
    "ja": "<start_lip_sync n01419 _normal m00001>「ハッパ！　<cs_pchero>！\n　戻るわよ！<stop_lip_animation n01419 CLOSE_MOUTH>",
    "ko": "<start_lip_sync n01419 _normal m00001>: 합파! <cs_pchero>!\n　돌아가자!<stop_lip_animation n01419 CLOSE_MOUTH>",
    "zh-hans": "<start_lip_sync n01419 _normal m00001>叶！<cs_pchero>！\n回去啦！<stop_lip_animation n01419 CLOSE_MOUTH>",
    "zh-hant": "<start_lip_sync n01419 _normal m00001>阿葉！<cs_pchero>！\n回去囉！<stop_lip_animation n01419 CLOSE_MOUTH>"
  },
  "18600": {
    "de": "",
    "en": "",
    "es": "",
    "fr": "",
    "it": "",
    "ja": "<start_lip_sync n01418 _normal m00001>「誰も　大樹を助けられない……。<stop_lip_animation n01418 CLOSE_MOUTH>",
    "ko": "<start_lip_sync n01418 _normal m00001>: 아무도 거목을 도울 수 없다니…….<stop_lip_animation n01418 CLOSE_MOUTH>",
    "zh-hans": "<start_lip_sync n01418 _normal m00001>谁也救不了大树……<stop_lip_animation n01418 CLOSE_MOUTH>",
    "zh-hant": "<start_lip_sync n01418 _normal m00001>誰也救不了大樹……<stop_lip_animation n01418 CLOSE_MOUTH>"
  },
  "18601": {
    "de": "",
    "en": "",
    "es": "",
    "fr": "",
    "it": "",
    "ja": "<start_lip_sync n01419 _normal m00001>「暗黒大樹と呼ばれてた樹が　世界樹だった……。\n　はるか昔から　魔瘴を取り込み　浄化していて\n　今　限界が　きているか……。<stop_lip_animation n01419 CLOSE_MOUTH>",
    "ko": "<start_lip_sync n01419 _normal m00001>: 암흑거목이라 불리던 나무가 세계수였다…….\n　먼 옛날부터 마장을 흡수하고 정화하다가\n　이제 한계에 도달했단 말이지…….<stop_lip_animation n01419 CLOSE_MOUTH>",
    "zh-hans": "<start_lip_sync n01419 _normal m00001>被称为黑暗大树的，其实是世界树……\n从古至今，不断吸收魔瘴并加以净化。\n现在已经到了极限吗……<stop_lip_animation n01419 CLOSE_MOUTH>",
    "zh-hant": "<start_lip_sync n01419 _normal m00001>過去被稱為黑暗大樹的，其實是世界樹……\n從古至今，不斷吸收魔瘴並加以淨化。\n如今已經到了極限嗎……<stop_lip_animation n01419 CLOSE_MOUTH>"
  },
  "18602": {
    "de": "",
    "en": "",
    "es": "",
    "fr": "",
    "it": "",
    "ja": "<start_lip_sync n01418 _normal m00001>「は…博士さん？<stop_lip_animation n01418 CLOSE_MOUTH>",
    "ko": "<start_lip_sync n01418 _normal m00001>: 바… 박사님?<stop_lip_animation n01418 CLOSE_MOUTH>",
    "zh-hans": "<start_lip_sync n01418 _normal m00001>博……博士姐姐？<stop_lip_animation n01418 CLOSE_MOUTH>",
    "zh-hant": "<start_lip_sync n01418 _normal m00001>博……博士姊姊？<stop_lip_animation n01418 CLOSE_MOUTH>"
  },
  "18603": {
    "de": "",
    "en": "",
    "es": "",
    "fr": "",
    "it": "",
    "ja": "<start_lip_sync n01419 _normal m00001>「……あたしの研究は　ムダだったってわけね。\n　魔瘴の増加は　おさえられないし\n　もう　あたしたちは終わりなのかしら……。<stop_lip_animation n01419 CLOSE_MOUTH>",
    "ko": "<start_lip_sync n01419 _normal m00001>: ……내 연구는 무용지물이었던 거야.\n　마장의 증가는 막을 수 없고\n　우린 이제 끝인 걸까…….<stop_lip_animation n01419 CLOSE_MOUTH>",
    "zh-hans": "<start_lip_sync n01419 _normal m00001>……我的研究白费时间了啊。\n无法抑制魔瘴的增加，\n我们这就算是要完了吗……<stop_lip_animation n01419 CLOSE_MOUTH>",
    "zh-hant": "<start_lip_sync n01419 _normal m00001>……所以我的研究毫無意義啊。\n無法抑制魔瘴的增加，\n我們這就算是要完了嗎……<stop_lip_animation n01419 CLOSE_MOUTH>"
  },
  "18604": {
    "de": "",
    "en": "",
    "es": "",
    "fr": "",
    "it": "",
    "ja": "<start_lip_sync n01418 _normal m00001>「ね…ねえ　博士さん！？<stop_lip_animation n01418 CLOSE_MOUTH>",
    "ko": "<start_lip_sync n01418 _normal m00001>: 저… 저기, 박사님!?<stop_lip_animation n01418 CLOSE_MOUTH>",
    "zh-hans": "<start_lip_sync n01418 _normal m00001>喂……喂！博士姐姐？！<stop_lip_animation n01418 CLOSE_MOUTH>",
    "zh-hant": "<start_lip_sync n01418 _normal m00001>博、博士姊姊……博士姊姊！？<stop_lip_animation n01418 CLOSE_MOUTH>"
  },
  "18605": {
    "de": "",
    "en": "",
    "es": "",
    "fr": "",
    "it": "",
    "ja": "<start_lip_sync n01419 _normal m00001>「あっ　ごめんね。ハッパ。\n　どしたの？<stop_lip_animation n01419 CLOSE_MOUTH>",
    "ko": "<start_lip_sync n01419 _normal m00001>: 앗, 미안해. 합파.\n　뭐라고 했니?<stop_lip_animation n01419 CLOSE_MOUTH>",
    "zh-hans": "<start_lip_sync n01419 _normal m00001>啊，抱歉啊。叶。\n怎么了？<stop_lip_animation n01419 CLOSE_MOUTH>",
    "zh-hant": "<start_lip_sync n01419 _normal m00001>啊，抱歉，阿葉。\n怎麼了嗎？<stop_lip_animation n01419 CLOSE_MOUTH>"
  },
  "18606": {
    "de": "",
    "en": "",
    "es": "",
    "fr": "",
    "it": "",
    "ja": "<start_lip_sync n01418 _normal m00001>「あ…あのね。\n　暗黒大樹の芯を覆う　魔瘴って\n　どうにか　できないかな？<stop_lip_animation n01418 CLOSE_MOUTH>",
    "ko": "<start_lip_sync n01418 _normal m00001>: 이… 있잖아.\n　암흑거목의 중심을 뒤덮은 마장을\n　어떻게 해결할 수 없을까?<stop_lip_animation n01418 CLOSE_MOUTH>",
    "zh-hans": "<start_lip_sync n01418 _normal m00001>那……那个啊。\n覆盖在黑暗大树树芯的魔瘴，\n真的没办法对付吗？<stop_lip_animation n01418 CLOSE_MOUTH>",
    "zh-hant": "<start_lip_sync n01418 _normal m00001>那……那個啊。\n覆蓋在黑暗大樹樹芯的魔瘴，\n真的沒辦法對付嗎？<stop_lip_animation n01418 CLOSE_MOUTH>"
  },
  "18607": {
    "de": "",
    "en": "",
    "es": "",
    "fr": "",
    "it": "",
    "ja": "<start_lip_sync n01419 _normal m00001>「えっ……？<stop_lip_animation n01419 CLOSE_MOUTH>",
    "ko": "<start_lip_sync n01419 _normal m00001>: 뭐……?<stop_lip_animation n01419 CLOSE_MOUTH>",
    "zh-hans": "<start_lip_sync n01419 _normal m00001>咦？<stop_lip_animation n01419 CLOSE_MOUTH>",
    "zh-hant": "<start_lip_sync n01419 _normal m00001>咦……？<stop_lip_animation n01419 CLOSE_MOUTH>"
  },
  "18608": {
    "de": "",
    "en": "",
    "es": "",
    "fr": "",
    "it": "",
    "ja": "<start_lip_sync n01418 _normal m00001>「大樹の芯から　魔瘴がなくなれば\n　魔瘴を取り込むチカラが　回復するんでしょ？<stop_lip_animation n01418 CLOSE_MOUTH>",
    "ko": "<start_lip_sync n01418 _normal m00001>: 거목의 중심에서 마장이 없어지면\n　다시 마장을 빨아들일 힘이 생기잖아?<stop_lip_animation n01418 CLOSE_MOUTH>",
    "zh-hans": "<start_lip_sync n01418 _normal m00001>把魔瘴从大树树芯清掉的话，\n应该就能恢复净化魔瘴的力量了吧？<stop_lip_animation n01418 CLOSE_MOUTH>",
    "zh-hant": "<start_lip_sync n01418 _normal m00001>只要把魔瘴從大樹樹芯清掉的話，\n應該就能恢復吸收魔瘴的力量了吧？<stop_lip_animation n01418 CLOSE_MOUTH>"
  },
  "18609": {
    "de": "",
    "en": "",
    "es": "",
    "fr": "",
    "it": "",
    "ja": "<start_lip_sync n01418 _normal m00001>「そしたら　各地に現れた魔瘴も\n　また　暗黒大樹が取り込んで　浄化するように\n　なるかもしれないし……。方法は　ないかな？<stop_lip_animation n01418 CLOSE_MOUTH>",
    "ko": "<start_lip_sync n01418 _normal m00001>: 그러면 각지에 나타난 마장도\n　다시 암흑거목이 빨아들여서 정화해\n　줄지도 모르고……. 무슨 방법이 없을까?<stop_lip_animation n01418 CLOSE_MOUTH>",
    "zh-hans": "<start_lip_sync n01418 _normal m00001>这样，黑暗大树说不定就又能吸收净化\n出现在各地的魔瘴……\n有什么办法清理树芯吗？<stop_lip_animation n01418 CLOSE_MOUTH>",
    "zh-hant": "<start_lip_sync n01418 _normal m00001>這麼一來，黑暗大樹說不定又能吸收\n各地出現的魔瘴並加以淨化……\n有什麼辦法清理樹芯嗎？<stop_lip_animation n01418 CLOSE_MOUTH>"
  },
  "18610": {
    "de": "",
    "en": "",
    "es": "",
    "fr": "",
    "it": "",
    "ja": "<start_lip_sync n01419 _normal m00001>「多くの研究者が　今も\n　魔瘴を　消滅させる方法を調べてるけど\n　まだ　誰にも突き止められてないのよ……。<stop_lip_animation n01419 CLOSE_MOUTH>",
    "ko": "<start_lip_sync n01419 _normal m00001>: 많은 연구자들이 지금도\n　마장을 소멸시킬 방법을 찾고 있지만\n　아직 아무도 알아내지 못했어…….<stop_lip_animation n01419 CLOSE_MOUTH>",
    "zh-hans": "<start_lip_sync n01419 _normal m00001>众多的研究者\n一直在调查消灭魔瘴的方法。\n可惜谁也没能找到啊……<stop_lip_animation n01419 CLOSE_MOUTH>",
    "zh-hant": "<start_lip_sync n01419 _normal m00001>眾多的研究者\n一直在調查消滅魔瘴的方法。\n可惜誰也沒能找到……<stop_lip_animation n01419 CLOSE_MOUTH>"
  },
  "18611": {
    "de": "",
    "en": "",
    "es": "",
    "fr": "",
    "it": "",
    "ja": "<start_lip_sync n01419 _normal m00001>「もう　時間も残されてないし\n　今から調べても　間に合わないわ……。<stop_lip_animation n01419 CLOSE_MOUTH>",
    "ko": "<start_lip_sync n01419 _normal m00001>: 이미 시간도 얼마 남지 않았고\n　지금부터 조사해도 늦을 거야…….<stop_lip_animation n01419 CLOSE_MOUTH>",
    "zh-hans": "<start_lip_sync n01419 _normal m00001>而且已经没有时间了，\n现在开始调查也来不及了啊……<stop_lip_animation n01419 CLOSE_MOUTH>",
    "zh-hant": "<start_lip_sync n01419 _normal m00001>而且時間已經所剩不多，\n現在開始調查也來不及了……<stop_lip_animation n01419 CLOSE_MOUTH>"
  },
  "18612": {
    "de": "",
    "en": "",
    "es": "",
    "fr": "",
    "it": "",
    "ja": "<start_lip_sync n01418 _normal m00001>「そうなの？\n　でも　博士さんなら　きっと　できるよ。<stop_lip_animation n01418 CLOSE_MOUTH>",
    "ko": "<start_lip_sync n01418 _normal m00001>: 그런가?\n　하지만 박사님이라면 분명 할 수 있어.<stop_lip_animation n01418 CLOSE_MOUTH>",
    "zh-hans": "<start_lip_sync n01418 _normal m00001>是吗？\n可我觉得博士姐姐一定会有办法的。<stop_lip_animation n01418 CLOSE_MOUTH>",
    "zh-hant": "<start_lip_sync n01418 _normal m00001>是嗎？\n但我覺得博士姊姊一定會有辦法的。<stop_lip_animation n01418 CLOSE_MOUTH>"
  },
  "18613": {
    "de": "",
    "en": "",
    "es": "",
    "fr": "",
    "it": "",
    "ja": "<start_lip_sync n01419 _normal m00001>「そ…そう？<stop_lip_animation n01419 CLOSE_MOUTH>",
    "ko": "<start_lip_sync n01419 _normal m00001>: 그… 그렇게 생각해?<stop_lip_animation n01419 CLOSE_MOUTH>",
    "zh-hans": "<start_lip_sync n01419 _normal m00001>是……是吗？<stop_lip_animation n01419 CLOSE_MOUTH>",
    "zh-hant": "<start_lip_sync n01419 _normal m00001>是……是嗎？<stop_lip_animation n01419 CLOSE_MOUTH>"
  },
  "18614": {
    "de": "",
    "en": "",
    "es": "",
    "fr": "",
    "it": "",
    "ja": "<start_lip_sync n01418 _normal m00001>「そうだよ！\n　だって　博士さんは天才だもん！<stop_lip_animation n01418 CLOSE_MOUTH>",
    "ko": "<start_lip_sync n01418 _normal m00001>: 당연하지!\n　왜냐하면 박사님은 천재인걸!<stop_lip_animation n01418 CLOSE_MOUTH>",
    "zh-hans": "<start_lip_sync n01418 _normal m00001>是啊！\n博士姐姐你是天才啊！<stop_lip_animation n01418 CLOSE_MOUTH>",
    "zh-hant": "<start_lip_sync n01418 _normal m00001>那當然！\n因為博士姊姊是天才啊！<stop_lip_animation n01418 CLOSE_MOUTH>"
  },
  "18615": {
    "de": "",
    "en": "",
    "es": "",
    "fr": "",
    "it": "",
    "ja": "<start_lip_sync n01419 _normal m00001>「天…才……？\n　あたしは　天才……。<stop_lip_animation n01419 CLOSE_MOUTH>",
    "ko": "<start_lip_sync n01419 _normal m00001>: 천…재……?\n　내가 천재라고…….<stop_lip_animation n01419 CLOSE_MOUTH>",
    "zh-hans": "<start_lip_sync n01419 _normal m00001>……天……才？\n我……是天才……<stop_lip_animation n01419 CLOSE_MOUTH>",
    "zh-hant": "<start_lip_sync n01419 _normal m00001>天……才……？\n我是天才……<stop_lip_animation n01419 CLOSE_MOUTH>"
  },
  "18616": {
    "de": "",
    "en": "",
    "es": "",
    "fr": "",
    "it": "",
    "ja": "<start_lip_sync n01419 _normal m00001>「へへ！　そうよね！\n　まだ　終わったわけじゃないわ！<stop_lip_animation n01419 CLOSE_MOUTH>",
    "ko": "<start_lip_sync n01419 _normal m00001>: 헤헤! 맞아!\n　아직 끝나지 않았어!<stop_lip_animation n01419 CLOSE_MOUTH>",
    "zh-hans": "<start_lip_sync n01419 _normal m00001>嘿嘿！也对啊！\n还没到完蛋的时候嘛！<stop_lip_animation n01419 CLOSE_MOUTH>",
    "zh-hant": "<start_lip_sync n01419 _normal m00001>嘿嘿！說的也是！\n還沒到完蛋的時候嘛！<stop_lip_animation n01419 CLOSE_MOUTH>"
  },
  "18617": {
    "de": "",
    "en": "",
    "es": "",
    "fr": "",
    "it": "",
    "ja": "<start_lip_sync n01419 _normal m00001>「魔瘴を消滅させる方法さえ　突き止めれば\n　いいんだし　こんなの楽勝だわ！<stop_lip_animation n01419 CLOSE_MOUTH>",
    "ko": "<start_lip_sync n01419 _normal m00001>: 마장을 소멸시킬 방법만 알아내면\n　되잖아? 이 정도는 식은 죽 먹기지!<stop_lip_animation n01419 CLOSE_MOUTH>",
    "zh-hans": "<start_lip_sync n01419 _normal m00001>只要找到消灭魔瘴的方法不就可以了嘛。\n这种小事轻而易举啦！<stop_lip_animation n01419 CLOSE_MOUTH>",
    "zh-hant": "<start_lip_sync n01419 _normal m00001>只要找出消滅魔瘴的方法就行了。\n這種小事輕而易舉啦！<stop_lip_animation n01419 CLOSE_MOUTH>"
  },
  "18618": {
    "de": "",
    "en": "",
    "es": "",
    "fr": "",
    "it": "",
    "ja": "<start_lip_sync n01419 _normal m00001>「よーし！　いちから出直しよ！\n　魔瘴を消滅させる方法は　あたしが\n　なんとしてでも　つかんでみせる！<stop_lip_animation n01419 CLOSE_MOUTH>",
    "ko": "<start_lip_sync n01419 _normal m00001>: 좋았어~! 처음부터 다시 시작하자!\n　마장을 소멸시킬 방법은 내가\n　어떻게든 찾아내겠어!<stop_lip_animation n01419 CLOSE_MOUTH>",
    "zh-hans": "<start_lip_sync n01419 _normal m00001>好！从头开始来过！\n我说什么也要找到\n消灭魔瘴的方法给你看！<stop_lip_animation n01419 CLOSE_MOUTH>",
    "zh-hant": "<start_lip_sync n01419 _normal m00001>好──！從頭來過！\n我說什麼也要找到\n消滅魔瘴的方法！<stop_lip_animation n01419 CLOSE_MOUTH>"
  },
  "18619": {
    "de": "",
    "en": "",
    "es": "",
    "fr": "",
    "it": "",
    "ja": "<start_lip_sync n01419 _normal m00001>「ハッパ！　お使いよ！<stop_lip_animation n01419 CLOSE_MOUTH>",
    "ko": "<start_lip_sync n01419 _normal m00001>: 합파! 심부름이다!<stop_lip_animation n01419 CLOSE_MOUTH>",
    "zh-hans": "<start_lip_sync n01419 _normal m00001>叶！有工作给你啦！<stop_lip_animation n01419 CLOSE_MOUTH>",
    "zh-hant": "<start_lip_sync n01419 _normal m00001>阿葉！幫忙跑個腿！<stop_lip_animation n01419 CLOSE_MOUTH>"
  },
  "18620": {
    "de": "",
    "en": "",
    "es": "",
    "fr": "",
    "it": "",
    "ja": "<start_lip_sync n01419 _normal m00001>「ハラが減っては　いくさは　できぬってね！\n　なんか　栄養のあるもの買ってきて！<stop_lip_animation n01419 CLOSE_MOUTH>",
    "ko": "<start_lip_sync n01419 _normal m00001>: 배가 고프면 싸울 수도 없는 법!\n　뭔가 영양가 있는 것 좀 사 와!<stop_lip_animation n01419 CLOSE_MOUTH>",
    "zh-hans": "<start_lip_sync n01419 _normal m00001>饿着肚子没法打仗！\n去买点有营养的东西来！<stop_lip_animation n01419 CLOSE_MOUTH>",
    "zh-hant": "<start_lip_sync n01419 _normal m00001>餓著肚子沒法打仗！\n去買點有營養的東西來！<stop_lip_animation n01419 CLOSE_MOUTH>"
  },
  "18621": {
    "de": "",
    "en": "",
    "es": "",
    "fr": "",
    "it": "",
    "ja": "<start_lip_sync n01418 _normal m00001>「うん！　わかった！<stop_lip_animation n01418 CLOSE_MOUTH>",
    "ko": "<start_lip_sync n01418 _normal m00001>: 응! 알았어!<stop_lip_animation n01418 CLOSE_MOUTH>",
    "zh-hans": "<start_lip_sync n01418 _normal m00001>嗯！明白了！<stop_lip_animation n01418 CLOSE_MOUTH>",
    "zh-hant": "<start_lip_sync n01418 _normal m00001>嗯！知道了！<stop_lip_animation n01418 CLOSE_MOUTH>"
  },
  "18622": {
    "de": "",
    "en": "",
    "es": "",
    "fr": "",
    "it": "",
    "ja": "<start_lip_sync n01418 _normal m00001>「えへへ！　暗黒大樹に\n　連れてってくれて　ありがとね！\n　これ！　ボクからの　お礼だよ！<stop_lip_animation n01418 CLOSE_MOUTH>",
    "ko": "<start_lip_sync n01418 _normal m00001>: 에헤헤! 암흑거목에\n　데려다줘서 고마워!\n　이거! 내가 주는 답례야!<stop_lip_animation n01418 CLOSE_MOUTH>",
    "zh-hans": "<start_lip_sync n01418 _normal m00001>诶嘿嘿！谢谢你带我去黑暗大树啊！\n这个是我的谢礼！\n请收下！<stop_lip_animation n01418 CLOSE_MOUTH>",
    "zh-hant": "<start_lip_sync n01418 _normal m00001>耶嘿嘿！謝謝你\n帶我去黑暗大樹啊！\n這是我要給你的謝禮！<stop_lip_animation n01418 CLOSE_MOUTH>"
  },
  "42173": {
    "de": "",
    "en": "",
    "es": "",
    "fr": "",
    "it": "",
    "ja": "クエスト『<%sEV_QUEST_NAME>』を\nクリアしました！\n　<update_quedate><open_irai>",
    "ko": "퀘스트\n『{%sEV_QUEST_NAME}|hpp(』을,』를)\n클리어했습니다!\n　<update_quedate><open_irai>",
    "zh-hans": "完成任务“<%sEV_QUEST_NAME>”了！\n<update_quedate><open_irai>",
    "zh-hant": "完成任務「<%sEV_QUEST_NAME>」了！\n<update_quedate><open_irai>"
  },
  "18623": {
    "de": "",
    "en": "",
    "es": "",
    "fr": "",
    "it": "",
    "ja": "<start_lip_sync n01418 _normal m00001>「えへへ！\n　ボク　買い物　行ってくるね！<stop_lip_animation n01418 CLOSE_MOUTH>",
    "ko": "<start_lip_sync n01418 _normal m00001>: 에헤헤!\n　난 심부름 다녀올게!<stop_lip_animation n01418 CLOSE_MOUTH>",
    "zh-hans": "<start_lip_sync n01418 _normal m00001>诶嘿嘿！\n我去买东西啦！<stop_lip_animation n01418 CLOSE_MOUTH>",
    "zh-hant": "<start_lip_sync n01418 _normal m00001>耶嘿嘿！\n那我去買東西囉！<stop_lip_animation n01418 CLOSE_MOUTH>"
  }
}
