{
  "15910": {
    "de": "",
    "en": "",
    "es": "",
    "fr": "",
    "it": "",
    "ja": "<start_lip_sync n00001 _normal m00001>「……やれやれ。\n　どうあっても　最後まで見届けねば\n　気が済まぬようじゃな。<stop_lip_animation n00001 CLOSE_MOUTH>",
    "ko": "<start_lip_sync n00001 _normal m00001>: ……나 원.\n　기어이 끝까지 확인해야\n　속이 후련하겠나?<stop_lip_animation n00001 CLOSE_MOUTH>",
    "zh-Hans": "<start_lip_sync n00001 _normal m00001>……哎呀哎呀。\n看样子，还真是\n不到最后不罢休啊。<stop_lip_animation n00001 CLOSE_MOUTH>",
    "zh-Hant": "<start_lip_sync n00001 _normal m00001>……真是的，\n看來還真是\n不到最後不干休啊。<stop_lip_animation n00001 CLOSE_MOUTH>"
  },
  "15911": {
    "de": "",
    "en": "",
    "es": "",
    "fr": "",
    "it": "",
    "ja": "<start_lip_sync n00004 _normal m00001>「こ　これは　エイドスさま。\n　今回は　どうなさったのです？<stop_lip_animation n00004 CLOSE_MOUTH>",
    "ko": "<start_lip_sync n00004 _normal m00001>: 에, 에이도스 님 아니십니까.\n　이번에는 무슨 일이십니까?<stop_lip_animation n00004 CLOSE_MOUTH>",
    "zh-Hans": "<start_lip_sync n00004 _normal m00001>艾、艾伊德斯大人。\n您这次来，有何贵干？<stop_lip_animation n00004 CLOSE_MOUTH>",
    "zh-Hant": "<start_lip_sync n00004 _normal m00001>艾、艾伊德斯大人。\n您這次來是怎麼了嗎？<stop_lip_animation n00004 CLOSE_MOUTH>"
  },
  "15912": {
    "de": "",
    "en": "",
    "es": "",
    "fr": "",
    "it": "",
    "ja": "<start_lip_sync n00001 _normal m00001>「そろそろ　オーレンが　ベコン渓谷に\n　戻る頃合いじゃろうと思ってな……。<stop_lip_animation n00001 CLOSE_MOUTH>",
    "ko": "<start_lip_sync n00001 _normal m00001>: 이제 슬슬 오렌이 베콘 계곡으로\n　돌아올 때가 되었으니…….<stop_lip_animation n00001 CLOSE_MOUTH>",
    "zh-Hans": "<start_lip_sync n00001 _normal m00001>我估算着，现在奥连\n差不多已经回到贝孔峡谷了。<stop_lip_animation n00001 CLOSE_MOUTH>",
    "zh-Hant": "<start_lip_sync n00001 _normal m00001>我只是想，\n奧連也差不多要回到貝孔溪谷了……<stop_lip_animation n00001 CLOSE_MOUTH>"
  },
  "15913": {
    "de": "",
    "en": "",
    "es": "",
    "fr": "",
    "it": "",
    "ja": "<start_lip_sync n00001 _normal m00001>「おおかた　また　お前さんたちが\n　余計なことを　考えているだろうと\n　こうして　やってきたのじゃ。<stop_lip_animation n00001 CLOSE_MOUTH>",
    "ko": "<start_lip_sync n00001 _normal m00001>: 자네들이 또\n　쓸데없는 짓을 하려 들 것 같아\n　이렇게 찾아온 걸세.<stop_lip_animation n00001 CLOSE_MOUTH>",
    "zh-Hans": "<start_lip_sync n00001 _normal m00001>我想你们大概\n还在想着多余的事吧。\n所以来这里看看。<stop_lip_animation n00001 CLOSE_MOUTH>",
    "zh-Hant": "<start_lip_sync n00001 _normal m00001>我想你們大概\n還在想著多餘的事吧。\n所以來這裡看看。<stop_lip_animation n00001 CLOSE_MOUTH>"
  },
  "15914": {
    "de": "",
    "en": "",
    "es": "",
    "fr": "",
    "it": "",
    "ja": "<start_lip_sync n00004 _normal m00001>「いや　そのう……ハッハッハッ。\n　さすがは　エイドスさま。ご明察ですなぁ。<stop_lip_animation n00004 CLOSE_MOUTH>",
    "ko": "<start_lip_sync n00004 _normal m00001>: 아이고, 참…… 하하하.\n　역시 에이도스 님이십니다.\n　다 꿰뚫어 보셨군요.<stop_lip_animation n00004 CLOSE_MOUTH>",
    "zh-Hans": "<start_lip_sync n00004 _normal m00001>没……那个……哈哈哈。\n不愧是艾伊德斯大人。真是明察秋毫啊。<stop_lip_animation n00004 CLOSE_MOUTH>",
    "zh-Hant": "<start_lip_sync n00004 _normal m00001>哎呀，那個……哈哈哈。\n不愧是艾伊德斯大人，真是明察秋毫啊。<stop_lip_animation n00004 CLOSE_MOUTH>"
  },
  "15915": {
    "de": "",
    "en": "",
    "es": "",
    "fr": "",
    "it": "",
    "ja": "<start_lip_sync n00001 _normal m00001>「……ふん。止めたところで　無駄なのは\n　よ～く　わかっておるわい。<stop_lip_animation n00001 CLOSE_MOUTH>",
    "ko": "<start_lip_sync n00001 _normal m00001>: ……흥, 말려 봤자 소용없다는 건\n　이미 잘 알고 있네.<stop_lip_animation n00001 CLOSE_MOUTH>",
    "zh-Hans": "<start_lip_sync n00001 _normal m00001>……哼。\n我就知道，阻止你们也没用。<stop_lip_animation n00001 CLOSE_MOUTH>",
    "zh-Hant": "<start_lip_sync n00001 _normal m00001>……哼。\n我就知道，阻止你們也沒用。<stop_lip_animation n00001 CLOSE_MOUTH>"
  },
  "15916": {
    "de": "",
    "en": "",
    "es": "",
    "fr": "",
    "it": "",
    "ja": "<start_lip_sync n00001 _normal m00001>「今回は　わしも　同行させてもらおう。\n　お前さんが　余計な手出しをせんように\n　見張らせてもらおう。<stop_lip_animation n00001 CLOSE_MOUTH>",
    "ko": "<start_lip_sync n00001 _normal m00001>: 이번에는 나도 함께 가겠네.\n　저 녀석이 쓸데없는 짓을 하지 못하도록\n　똑똑히 감시해야 하니까.<stop_lip_animation n00001 CLOSE_MOUTH>",
    "zh-Hans": "<start_lip_sync n00001 _normal m00001>这次也让我一路同行吧。\n我会盯着你们，\n不让你们多管闲事的。<stop_lip_animation n00001 CLOSE_MOUTH>",
    "zh-Hant": "<start_lip_sync n00001 _normal m00001>這次也讓我一路同行吧。\n我會盯著你們，\n不讓你們多管閒事的。<stop_lip_animation n00001 CLOSE_MOUTH>"
  },
  "15917": {
    "de": "",
    "en": "",
    "es": "",
    "fr": "",
    "it": "",
    "ja": "<start_lip_sync n00001 _normal m00001>「フフン。止めても　無駄じゃぞ。\n　では　わしは　先に行っておるからな。\n　あまり　待たせるでないぞ！<stop_lip_animation n00001 CLOSE_MOUTH>",
    "ko": "<start_lip_sync n00001 _normal m00001>: 흥, 말려도 소용없네.\n　그럼 난 먼저 출발할 테니\n　너도 너무 늦지 말거라!<stop_lip_animation n00001 CLOSE_MOUTH>",
    "zh-Hans": "<start_lip_sync n00001 _normal m00001>哼哼。可别想拦住我。\n那我先行一步。\n可别让我等太久啊！<stop_lip_animation n00001 CLOSE_MOUTH>",
    "zh-Hant": "<start_lip_sync n00001 _normal m00001>哼哼，可別想攔住我。\n那我先行一步了。\n可別讓我等太久啊！<stop_lip_animation n00001 CLOSE_MOUTH>"
  },
  "15918": {
    "de": "",
    "en": "",
    "es": "",
    "fr": "",
    "it": "",
    "ja": "<start_lip_sync n00001 _normal m00001>「遅いぞ　<cs_pchero>。\n　ほれっ！　あれを見てみい。<stop_lip_animation n00001 CLOSE_MOUTH>",
    "ko": "<start_lip_sync n00001 _normal m00001>: 왜 이리 늦었느냐, <cs_pchero>.\n　자! 저걸 보거라.<stop_lip_animation n00001 CLOSE_MOUTH>",
    "zh-Hans": "<start_lip_sync n00001 _normal m00001>真够慢的，<cs_pchero>。\n喏！看那个。<stop_lip_animation n00001 CLOSE_MOUTH>",
    "zh-Hant": "<start_lip_sync n00001 _normal m00001>真夠慢的，<cs_pchero>。\n好啦！看看那個。<stop_lip_animation n00001 CLOSE_MOUTH>"
  },
  "15919": {
    "de": "",
    "en": "",
    "es": "",
    "fr": "",
    "it": "",
    "ja": "<start_lip_sync m50004 _normal m00001>「ずいぶん長い間　待たせてしまったな……。<stop_lip_animation m50004 CLOSE_MOUTH>",
    "ko": "<start_lip_sync m50004 _normal m00001>: 오래 기다리게 해서 미안하다…….<stop_lip_animation m50004 CLOSE_MOUTH>",
    "zh-Hans": "<start_lip_sync m50004 _normal m00001>实在让你们久等了……<stop_lip_animation m50004 CLOSE_MOUTH>",
    "zh-Hant": "<start_lip_sync m50004 _normal m00001>實在讓你們久等了……<stop_lip_animation m50004 CLOSE_MOUTH>"
  },
  "15920": {
    "de": "",
    "en": "",
    "es": "",
    "fr": "",
    "it": "",
    "ja": "<start_lip_sync m50004 _normal m00001>「このグロリスのしずくを　かければ\n　魔瘴に侵された　お前たちを　\n　救ってやることが　できるはず。<stop_lip_animation m50004 CLOSE_MOUTH>",
    "ko": "<start_lip_sync m50004 _normal m00001>: 이 글로리스의 물방울을 뿌리면\n　마장에 중독된 너희를 구할 수 있을 터.<stop_lip_animation m50004 CLOSE_MOUTH>",
    "zh-Hans": "<start_lip_sync m50004 _normal m00001>只要洒上古洛里斯花露，\n就应该能拯救\n被魔瘴侵害的你们。<stop_lip_animation m50004 CLOSE_MOUTH>",
    "zh-Hant": "<start_lip_sync m50004 _normal m00001>只要灑上古洛里斯之露，\n應該就能拯救\n被魔瘴侵蝕的你們。<stop_lip_animation m50004 CLOSE_MOUTH>"
  },
  "15921": {
    "de": "",
    "en": "",
    "es": "",
    "fr": "",
    "it": "",
    "ja": "オーレンは　グロリスのしずくを\nガイコツたちに　振りまいた。",
    "ko": "오렌은 글로리스의 물방울을\n해골들에게 뿌렸다.",
    "zh-Hans": "奥连将古洛里斯花露\n洒向骷髅们。",
    "zh-Hant": "奧連將古洛里斯之露\n灑向骸骨們。"
  },
  "16056": {
    "de": "",
    "en": "",
    "es": "",
    "fr": "",
    "it": "",
    "ja": "<start_lip_sync m04900 _normal m00001>「おぉぉぉ……オ……レン様ぁ……。<stop_lip_animation m04900 CLOSE_MOUTH>",
    "ko": "<start_lip_sync m04900 _normal m00001>: 으오오오…… 오……렌 님…….<stop_lip_animation m04900 CLOSE_MOUTH>",
    "zh-Hans": "<start_lip_sync m04900 _normal m00001>噢……奥……连大人……<stop_lip_animation m04900 CLOSE_MOUTH>",
    "zh-Hant": "<start_lip_sync m04900 _normal m00001>喔喔喔喔……奧……連大人……<stop_lip_animation m04900 CLOSE_MOUTH>"
  },
  "15923": {
    "de": "",
    "en": "",
    "es": "",
    "fr": "",
    "it": "",
    "ja": "<start_lip_sync m50004 _normal m00001>「バ　バカな……。\n　グロリスのしずくを　浴びせれば\n　すべて　うまくいくはず……。<stop_lip_animation m50004 CLOSE_MOUTH>",
    "ko": "<start_lip_sync m50004 _normal m00001>: 이, 이럴 수가…….\n　글로리스의 물방울을 뿌리면\n　부하들을 구할 수 있는 것 아니었나……?<stop_lip_animation m50004 CLOSE_MOUTH>",
    "zh-Hans": "<start_lip_sync m50004 _normal m00001>不、不可能……\n既然被花露浇到，\n一切都应该好起来啊……<stop_lip_animation m50004 CLOSE_MOUTH>",
    "zh-Hant": "<start_lip_sync m50004 _normal m00001>不、不可能……\n只要淋上古洛里斯之露，\n一切應該就會好起來了……<stop_lip_animation m50004 CLOSE_MOUTH>"
  },
  "15924": {
    "de": "",
    "en": "",
    "es": "",
    "fr": "",
    "it": "",
    "ja": "<start_lip_sync n00001 _normal m00001>「魔瘴に侵された亡者が　しずくを浴びれば\n　消え去るのは　道理じゃな。<stop_lip_animation n00001 CLOSE_MOUTH>",
    "ko": "<start_lip_sync n00001 _normal m00001>: 마장에 중독된 망자가 물방울에 닿으면\n　사라지는 것이 섭리.<stop_lip_animation n00001 CLOSE_MOUTH>",
    "zh-Hans": "<start_lip_sync n00001 _normal m00001>被魔瘴侵蚀的亡者，碰到花露后消失。\n这是理所当然的事。<stop_lip_animation n00001 CLOSE_MOUTH>",
    "zh-Hant": "<start_lip_sync n00001 _normal m00001>被魔瘴侵蝕的亡者碰到露水後便會消失。\n這是理所當然的事。<stop_lip_animation n00001 CLOSE_MOUTH>"
  },
  "15925": {
    "de": "",
    "en": "",
    "es": "",
    "fr": "",
    "it": "",
    "ja": "<start_lip_sync n00001 _normal m00001>「……今こそ　すべてを語ろう。\n　妖剣士オーレンが生まれた　そのわけを。<stop_lip_animation n00001 CLOSE_MOUTH>",
    "ko": "<start_lip_sync n00001 _normal m00001>: ……이제 모든 걸 얘기해 주마.\n　요검사 오렌이 탄생하게 된 경위를.<stop_lip_animation n00001 CLOSE_MOUTH>",
    "zh-Hans": "<start_lip_sync n00001 _normal m00001>……现在，我要将一切阐明。\n妖剑士奥连诞生的真相是这样的。<stop_lip_animation n00001 CLOSE_MOUTH>",
    "zh-Hant": "<start_lip_sync n00001 _normal m00001>……現在，我就來闡明一切吧。\n造就妖劍士奧連的原因。<stop_lip_animation n00001 CLOSE_MOUTH>"
  },
  "15926": {
    "de": "",
    "en": "",
    "es": "",
    "fr": "",
    "it": "",
    "ja": "<start_lip_sync n00001 _normal m00001>「グロリスのしずくを手に入れた　オーレンは\n　血と汗に　まみれながらも　部下たちが待つ\n　このベコン渓谷の奥地まで　たどり着いた。<stop_lip_animation n00001 CLOSE_MOUTH>",
    "ko": "<start_lip_sync n00001 _normal m00001>: 글로리스의 물방울을 손에 넣은 오렌은\n　피와 땀으로 범벅이 되어\n　부하들이 기다리는 이 베콘 계곡에 도착했다.<stop_lip_animation n00001 CLOSE_MOUTH>",
    "zh-Hans": "<start_lip_sync n00001 _normal m00001>得到古洛里斯花露的奥连\n淌着鲜血和汗水\n来到了部下被困的贝孔峡谷深处……<stop_lip_animation n00001 CLOSE_MOUTH>",
    "zh-Hant": "<start_lip_sync n00001 _normal m00001>得到古洛里斯之露的奧連\n淌著鮮血和汗水來到了\n部下們等著的貝孔溪谷深處。<stop_lip_animation n00001 CLOSE_MOUTH>"
  },
  "15927": {
    "de": "",
    "en": "",
    "es": "",
    "fr": "",
    "it": "",
    "ja": "<start_lip_sync n00001 _normal m00001>「オーレンが　そこで見たものは……\n　すでに　絶命し　魔瘴に侵されきって　\n　生ける屍と化した　部下たちの姿じゃった。<stop_lip_animation n00001 CLOSE_MOUTH>",
    "ko": "<start_lip_sync n00001 _normal m00001>: 하지만 오렌이 본 것은……\n　이미 마장에 완전히 중독되어\n　살아 있는 시체로 변한 부하들이었다.<stop_lip_animation n00001 CLOSE_MOUTH>",
    "zh-Hans": "<start_lip_sync n00001 _normal m00001>在那里，奥连看到的是……\n被魔瘴侵蚀、命丧黄泉，\n已成为行尸走肉的部下们。<stop_lip_animation n00001 CLOSE_MOUTH>",
    "zh-Hant": "<start_lip_sync n00001 _normal m00001>在那裡，奧連看到的是……\n被魔瘴侵蝕、命喪黃泉，\n已成為行屍走肉的部下們。<stop_lip_animation n00001 CLOSE_MOUTH>"
  },
  "15928": {
    "de": "",
    "en": "",
    "es": "",
    "fr": "",
    "it": "",
    "ja": "<start_lip_sync n00001 _normal m00001>「そして　その凶刃は　オーレンに向けられた。\n　肉体的にも　精神的にも　疲れきった\n　オーレンに　いったい　何ができようか？<stop_lip_animation n00001 CLOSE_MOUTH>",
    "ko": "<start_lip_sync n00001 _normal m00001>: 그리고 그 칼날은 오렌에게로 향했다.\n　몸도 마음도 지칠 대로 지친\n　오렌에게 무슨 수가 있었겠느냐?<stop_lip_animation n00001 CLOSE_MOUTH>",
    "zh-Hans": "<start_lip_sync n00001 _normal m00001>它们手持武器向奥连袭来。\n身心俱疲的奥连\n根本无从招架。<stop_lip_animation n00001 CLOSE_MOUTH>",
    "zh-Hant": "<start_lip_sync n00001 _normal m00001>牠們手持武器向奧連襲來。\n身心俱疲的奧連\n根本無從招架。<stop_lip_animation n00001 CLOSE_MOUTH>"
  },
  "15929": {
    "de": "",
    "en": "",
    "es": "",
    "fr": "",
    "it": "",
    "ja": "<start_lip_sync n00001 _normal m00001>「全身を　部下たちの剣で　斬り刻まれながら\n　オーレンは　絶叫したという……。<stop_lip_animation n00001 CLOSE_MOUTH>",
    "ko": "<start_lip_sync n00001 _normal m00001>: 부하들의 검에 온몸을 난자당하며\n　오렌은 절규했다고 한다…….<stop_lip_animation n00001 CLOSE_MOUTH>",
    "zh-Hans": "<start_lip_sync n00001 _normal m00001>奥连被部下用剑砍得遍体鳞伤，\n发出了声嘶力竭的哀嚎……<stop_lip_animation n00001 CLOSE_MOUTH>",
    "zh-Hant": "<start_lip_sync n00001 _normal m00001>最後被部下們的劍砍得遍體鱗傷，\n奧連發出了聲嘶力竭的哀號……<stop_lip_animation n00001 CLOSE_MOUTH>"
  },
  "16057": {
    "de": "",
    "en": "",
    "es": "",
    "fr": "",
    "it": "",
    "ja": "<start_lip_sync n01512 _normal m00001>「これが　お前たちを救ってやれなかった\n　私への罰ならば　よろこんで受けよう！<stop_lip_animation n01512 CLOSE_MOUTH>",
    "ko": "<start_lip_sync n01512 _normal m00001>: 이게 너희를 구하지 못한\n　내게 내리는 벌이라면 달게 받겠다!<stop_lip_animation n01512 CLOSE_MOUTH>",
    "zh-Hans": "<start_lip_sync n01512 _normal m00001>如果这是对我没能救你们的惩罚，\n那我欣然接受！<stop_lip_animation n01512 CLOSE_MOUTH>",
    "zh-Hant": "<start_lip_sync n01512 _normal m00001>如果這是對我沒能救你們的懲罰，\n那我欣然接受！<stop_lip_animation n01512 CLOSE_MOUTH>"
  },
  "16058": {
    "de": "",
    "en": "",
    "es": "",
    "fr": "",
    "it": "",
    "ja": "<start_lip_sync n01512 _normal m00001>「だが　たとえ　このまま死に果てようと\n　決して　私は　お前たちを見捨てたりせぬ！\n　死して後も　ともにあろうぞ！<stop_lip_animation n01512 CLOSE_MOUTH>",
    "ko": "<start_lip_sync n01512 _normal m00001>: 하지만 이대로 내 목숨이 끊어진다 해도\n　난 절대로 너희를 버리지 않을 것이다!\n　죽어서도 너희와 함께하겠다!<stop_lip_animation n01512 CLOSE_MOUTH>",
    "zh-Hans": "<start_lip_sync n01512 _normal m00001>但是，就算我这样死去也决不会抛下你们！！\n就算是死，也不会分离！<stop_lip_animation n01512 CLOSE_MOUTH>",
    "zh-Hant": "<start_lip_sync n01512 _normal m00001>但是，就算我這樣死去\n也絕不會拋下你們！\n就算是死，也不會分離！<stop_lip_animation n01512 CLOSE_MOUTH>"
  },
  "15932": {
    "de": "",
    "en": "",
    "es": "",
    "fr": "",
    "it": "",
    "ja": "<start_lip_sync n00001 _normal m00001>「こうして　妖剣士オーレンは　誕生した。\n　わしが　それらの出来事を知ったのは\n　すべてが　終わった後じゃった……。<stop_lip_animation n00001 CLOSE_MOUTH>",
    "ko": "<start_lip_sync n00001 _normal m00001>: 요검사 오렌은 그렇게 탄생한 것이다.\n　내가 이 일의 전말을 안 건\n　이미 모든 일이 벌어진 뒤였다…….<stop_lip_animation n00001 CLOSE_MOUTH>",
    "zh-Hans": "<start_lip_sync n00001 _normal m00001>于是，妖剑士奥连就这样诞生了。\n当我知道这件事的时候，\n一切都已经晚了……<stop_lip_animation n00001 CLOSE_MOUTH>",
    "zh-Hant": "<start_lip_sync n00001 _normal m00001>於是，妖劍士奧連就這樣誕生了。\n當我知道這件事的時候，\n一切都已經結束了……<stop_lip_animation n00001 CLOSE_MOUTH>"
  },
  "15933": {
    "de": "",
    "en": "",
    "es": "",
    "fr": "",
    "it": "",
    "ja": "<start_lip_sync n00001 _normal m00001>「わしに　迷惑が　かからぬよう\n　オーレンは　追われる身となったときから\n　わしとの連絡を　絶ったのじゃよ。<stop_lip_animation n00001 CLOSE_MOUTH>",
    "ko": "<start_lip_sync n00001 _normal m00001>: 나에게 피해가 갈 것을 우려한\n　오렌이 도망자 신세가 된 뒤로\n　나와의 연락을 끊었기 때문이었지.<stop_lip_animation n00001 CLOSE_MOUTH>",
    "zh-Hans": "<start_lip_sync n00001 _normal m00001>为了不给我添麻烦，\n奥连从被通缉的时候起，\n就再也没联系过我。<stop_lip_animation n00001 CLOSE_MOUTH>",
    "zh-Hant": "<start_lip_sync n00001 _normal m00001>為了不給我添麻煩，\n奧連從被通緝的時候起，\n就再也沒聯繫過我。<stop_lip_animation n00001 CLOSE_MOUTH>"
  },
  "15934": {
    "de": "",
    "en": "",
    "es": "",
    "fr": "",
    "it": "",
    "ja": "<start_lip_sync m50004 _normal m00001>「……オォオオォオオオォォ！！\n　なぜだ？　なぜ　こうなった！？\n　私は　なんのために　ここまで……。<stop_lip_animation m50004 CLOSE_MOUTH>",
    "ko": "<start_lip_sync m50004 _normal m00001>: ……으오오오오오오오오오!!\n　왜냐? 왜 이렇게 된 것이냐!?\n　난 무엇을 위해 지금까지…….<stop_lip_animation m50004 CLOSE_MOUTH>",
    "zh-Hans": "<start_lip_sync m50004 _normal m00001>……噢噢噢噢噢噢噢！！为什么？\n为什么会变成这样？！\n我走到这一步，究竟是为了什么……<stop_lip_animation m50004 CLOSE_MOUTH>",
    "zh-Hant": "<start_lip_sync m50004 _normal m00001>……喔喔喔喔喔喔喔喔喔喔！！\n為什麼？為什麼會變成這樣！？\n我走到這一步，究竟是為了什麼……<stop_lip_animation m50004 CLOSE_MOUTH>"
  },
  "15935": {
    "de": "",
    "en": "",
    "es": "",
    "fr": "",
    "it": "",
    "ja": "<start_lip_sync n00001 _normal m00001>「生前の記憶に囚われた　オーレンが\n　雲上湖に　向かったときから　\n　この結末は　わかりきっておった。<stop_lip_animation n00001 CLOSE_MOUTH>",
    "ko": "<start_lip_sync n00001 _normal m00001>: 생전의 기억에 사로잡힌 오렌이\n　운상호로 향했을 때부터\n　이리 되리라 예상했다.<stop_lip_animation n00001 CLOSE_MOUTH>",
    "zh-Hans": "<start_lip_sync n00001 _normal m00001>被生前记忆所困的奥连\n前往云上湖的时候，\n我就已经料到了这结局。<stop_lip_animation n00001 CLOSE_MOUTH>",
    "zh-Hant": "<start_lip_sync n00001 _normal m00001>受到生前記憶束縛的奧連\n前往雲上湖的時候，\n我就已經料到了這結局。<stop_lip_animation n00001 CLOSE_MOUTH>"
  },
  "15936": {
    "de": "",
    "en": "",
    "es": "",
    "fr": "",
    "it": "",
    "ja": "<start_lip_sync n00001 _normal m00001>「わかっていながら　わしには\n　あやつを止めることが　できんかった。<stop_lip_animation n00001 CLOSE_MOUTH>",
    "ko": "<start_lip_sync n00001 _normal m00001>: 하지만 그럼에도 나는\n　오렌을 막을 수 없었다.<stop_lip_animation n00001 CLOSE_MOUTH>",
    "zh-Hans": "<start_lip_sync n00001 _normal m00001>虽然我已心知肚明，\n但还是没能阻止他。<stop_lip_animation n00001 CLOSE_MOUTH>",
    "zh-Hant": "<start_lip_sync n00001 _normal m00001>雖然我已心知肚明，\n但還是沒能阻止牠。<stop_lip_animation n00001 CLOSE_MOUTH>"
  },
  "15937": {
    "de": "",
    "en": "",
    "es": "",
    "fr": "",
    "it": "",
    "ja": "<start_lip_sync n00001 _normal m00001>「……すまぬ　<cs_pchero>。\n　お前が　オーレンを止めてやってくれ！<stop_lip_animation n00001 CLOSE_MOUTH>",
    "ko": "<start_lip_sync n00001 _normal m00001>: ……미안하다, <cs_pchero>.\n　네가 오렌을 막아다오!<stop_lip_animation n00001 CLOSE_MOUTH>",
    "zh-Hans": "<start_lip_sync n00001 _normal m00001>……抱歉，<cs_pchero>。\n你去阻止奥连吧！<stop_lip_animation n00001 CLOSE_MOUTH>",
    "zh-Hant": "<start_lip_sync n00001 _normal m00001>……抱歉，<cs_pchero>。\n你去阻止奧連吧！<stop_lip_animation n00001 CLOSE_MOUTH>"
  },
  "15938": {
    "de": "",
    "en": "",
    "es": "",
    "fr": "",
    "it": "",
    "ja": "<start_lip_sync m50004 _normal m00001>「ウォオオォオオオォォ！！<stop_lip_animation m50004 CLOSE_MOUTH>",
    "ko": "<start_lip_sync m50004 _normal m00001>: 으오오오오오오오오오!!<stop_lip_animation m50004 CLOSE_MOUTH>",
    "zh-Hans": "<start_lip_sync m50004 _normal m00001>噢噢噢噢噢噢噢！！<stop_lip_animation m50004 CLOSE_MOUTH>",
    "zh-Hant": "<start_lip_sync m50004 _normal m00001>唔喔喔喔喔喔喔喔喔喔！！<stop_lip_animation m50004 CLOSE_MOUTH>"
  },
  "15939": {
    "de": "",
    "en": "",
    "es": "",
    "fr": "",
    "it": "",
    "ja": "<start_lip_sync n00001 _normal m00001>「戻ってきたか　<cs_pchero>。\n　……もはや　今のオーレンには\n　何を言っても　通じぬようだ。<stop_lip_animation n00001 CLOSE_MOUTH>",
    "ko": "<start_lip_sync n00001 _normal m00001>: 돌아왔느냐, <cs_pchero>.\n　……지금 오렌에게는\n　무슨 말을 건넨들 소용없을 거다.<stop_lip_animation n00001 CLOSE_MOUTH>",
    "zh-Hans": "<start_lip_sync n00001 _normal m00001>你回来了吗，<cs_pchero>。\n……现在跟奥连说什么\n都没有用了。<stop_lip_animation n00001 CLOSE_MOUTH>",
    "zh-Hant": "<start_lip_sync n00001 _normal m00001>回來了嗎？<cs_pchero>。\n……現在跟奧連說什麼\n都沒有用了。<stop_lip_animation n00001 CLOSE_MOUTH>"
  },
  "15940": {
    "de": "",
    "en": "",
    "es": "",
    "fr": "",
    "it": "",
    "ja": "<start_lip_sync n00001 _normal m00001>「こうなることを　予想はしていたが……。\n　すまんな　<cs_pchero>。\n　お前が　オーレンを　止めてやってくれ。<stop_lip_animation n00001 CLOSE_MOUTH>",
    "ko": "<start_lip_sync n00001 _normal m00001>: 이리 되리라 예상은 했다만…….\n　미안하다, <cs_pchero>.\n　네가 오렌을 막아다오.<stop_lip_animation n00001 CLOSE_MOUTH>",
    "zh-Hans": "<start_lip_sync n00001 _normal m00001>我已经想到会是这样了……\n抱歉，<cs_pchero>。\n你去阻止奥连吧。<stop_lip_animation n00001 CLOSE_MOUTH>",
    "zh-Hant": "<start_lip_sync n00001 _normal m00001>我雖然早就猜到會變這樣……\n抱歉，<cs_pchero>。\n你去阻止奧連吧。<stop_lip_animation n00001 CLOSE_MOUTH>"
  },
  "15941": {
    "de": "",
    "en": "",
    "es": "",
    "fr": "",
    "it": "",
    "ja": "<start_lip_sync m50004 _normal m00001>「……オォオオォオオオォォ！！\n　なぜだ？　なぜ　こうなった！？\n　私は　なんのために　ここまで……。<stop_lip_animation m50004 CLOSE_MOUTH>",
    "ko": "<start_lip_sync m50004 _normal m00001>: ……으오오오오오오오오오!!\n　왜냐? 왜 이렇게 된 것이냐!?\n　난 무엇을 위해 지금까지…….<stop_lip_animation m50004 CLOSE_MOUTH>",
    "zh-Hans": "<start_lip_sync m50004 _normal m00001>……噢噢噢噢噢噢噢！！为什么？\n为什么会变成这样？！\n我走到这一步，究竟是为了什么……<stop_lip_animation m50004 CLOSE_MOUTH>",
    "zh-Hant": "<start_lip_sync m50004 _normal m00001>……喔喔喔喔喔喔喔喔喔喔！！\n為什麼？為什麼會變成這樣！？\n我走到這一步，究竟是為了什麼……<stop_lip_animation m50004 CLOSE_MOUTH>"
  },
  "15942": {
    "de": "",
    "en": "",
    "es": "",
    "fr": "",
    "it": "",
    "ja": "<start_lip_sync m50004 _normal m00001>「ウォオオォオオオォォ！！<stop_lip_animation m50004 CLOSE_MOUTH>",
    "ko": "<start_lip_sync m50004 _normal m00001>: 으오오오오오오오오오!!<stop_lip_animation m50004 CLOSE_MOUTH>",
    "zh-Hans": "<start_lip_sync m50004 _normal m00001>噢噢噢噢噢噢噢！！<stop_lip_animation m50004 CLOSE_MOUTH>",
    "zh-Hant": "<start_lip_sync m50004 _normal m00001>唔喔喔喔喔喔喔喔喔喔！！<stop_lip_animation m50004 CLOSE_MOUTH>"
  },
  "15943": {
    "de": "",
    "en": "",
    "es": "",
    "fr": "",
    "it": "",
    "ja": "<start_lip_sync m50004 _normal m00001>「オオオォォォ……。\n　わ　私は　今まで　何を……？<stop_lip_animation m50004 CLOSE_MOUTH>",
    "ko": "<start_lip_sync m50004 _normal m00001>: 으오오오오오…….\n　나, 난 지금까지 대체 뭘……?<stop_lip_animation m50004 CLOSE_MOUTH>",
    "zh-Hans": "<start_lip_sync m50004 _normal m00001>噢噢噢噢噢噢噢……\n我、我至今，都在干什么……<stop_lip_animation m50004 CLOSE_MOUTH>",
    "zh-Hant": "<start_lip_sync m50004 _normal m00001>喔喔喔喔喔喔……\n我、我至今都在做什麼……？<stop_lip_animation m50004 CLOSE_MOUTH>"
  },
  "15944": {
    "de": "",
    "en": "",
    "es": "",
    "fr": "",
    "it": "",
    "ja": "<start_lip_sync n00001 _normal m00001>「すべて　終わったのじゃよ。\n　もう　眠りにつくがよい　オーレンよ。<stop_lip_animation n00001 CLOSE_MOUTH>",
    "ko": "<start_lip_sync n00001 _normal m00001>: 모두 끝났네.\n　이제 그만 편히 쉬게나, 오렌.<stop_lip_animation n00001 CLOSE_MOUTH>",
    "zh-Hans": "<start_lip_sync n00001 _normal m00001>一切都结束了。\n奥连啊，你可以安心地长眠了。<stop_lip_animation n00001 CLOSE_MOUTH>",
    "zh-Hant": "<start_lip_sync n00001 _normal m00001>一切都結束了。\n奧連啊，你可以安心地長眠了。<stop_lip_animation n00001 CLOSE_MOUTH>"
  },
  "15945": {
    "de": "",
    "en": "",
    "es": "",
    "fr": "",
    "it": "",
    "ja": "<start_lip_sync m50004 _normal m00001>「その声……お前は　エイドス！？<stop_lip_animation m50004 CLOSE_MOUTH>",
    "ko": "<start_lip_sync m50004 _normal m00001>: 그 목소리는…… 에이도스인가!?<stop_lip_animation m50004 CLOSE_MOUTH>",
    "zh-Hans": "<start_lip_sync m50004 _normal m00001>这声音……你是……艾伊德斯？<stop_lip_animation m50004 CLOSE_MOUTH>",
    "zh-Hant": "<start_lip_sync m50004 _normal m00001>這聲音……你是……艾伊德斯！？<stop_lip_animation m50004 CLOSE_MOUTH>"
  },
  "15946": {
    "de": "",
    "en": "",
    "es": "",
    "fr": "",
    "it": "",
    "ja": "<start_lip_sync m50004 _normal m00001>「……そうか　すべて　思いだしたぞ。\n　私は　すでに　死んだ身なのだな。<stop_lip_animation m50004 CLOSE_MOUTH>",
    "ko": "<start_lip_sync m50004 _normal m00001>: ……그래, 전부 기억났다.\n　난 이미 죽은 거였군.<stop_lip_animation m50004 CLOSE_MOUTH>",
    "zh-Hans": "<start_lip_sync m50004 _normal m00001>……原来如此，我都想起来了。\n我已经死了……<stop_lip_animation m50004 CLOSE_MOUTH>",
    "zh-Hant": "<start_lip_sync m50004 _normal m00001>……原來如此，我都想起來了。\n我已經死了吧。<stop_lip_animation m50004 CLOSE_MOUTH>"
  },
  "15947": {
    "de": "",
    "en": "",
    "es": "",
    "fr": "",
    "it": "",
    "ja": "<start_lip_sync m50004 _normal m00001>「わが部下たちは　先に逝ったのか……。\n　ならば　私も　逝ってやらねばな。\n　そう約束したのだから……。<stop_lip_animation m50004 CLOSE_MOUTH>",
    "ko": "<start_lip_sync m50004 _normal m00001>: 내 부하들은 먼저 간 건가…….\n　그렇다면 나도 따라가는 수밖에.\n　그렇게 약속했으니까…….<stop_lip_animation m50004 CLOSE_MOUTH>",
    "zh-Hans": "<start_lip_sync m50004 _normal m00001>我的部下已经先走了……\n那我也要走了……\n因为我们是这么约定的……<stop_lip_animation m50004 CLOSE_MOUTH>",
    "zh-Hant": "<start_lip_sync m50004 _normal m00001>我的部下已經先走了嗎……\n那我也得走了。\n因為我們是這麼約定的……<stop_lip_animation m50004 CLOSE_MOUTH>"
  },
  "15948": {
    "de": "",
    "en": "",
    "es": "",
    "fr": "",
    "it": "",
    "ja": "<start_lip_sync n00001 _normal m00001>「……あの日　わしは　オーレンに\n　魔瘴を打ち消す方法を　教えただけで\n　自分の役目を果たしたと　満足していた。<stop_lip_animation n00001 CLOSE_MOUTH>",
    "ko": "<start_lip_sync n00001 _normal m00001>: ……그때 난 오렌에게\n　마장을 상쇄시킬 방법을 알려준 것으로\n　내 할 일을 다 했다며 만족해했다.<stop_lip_animation n00001 CLOSE_MOUTH>",
    "zh-Hans": "<start_lip_sync n00001 _normal m00001>……那天，我只是\n告诉了奥连除去魔瘴的方法，\n就觉得自己帮上了忙，非常满足。<stop_lip_animation n00001 CLOSE_MOUTH>",
    "zh-Hant": "<start_lip_sync n00001 _normal m00001>……那天，我只是\n告訴了奧連抵銷魔瘴的方法，\n就覺得自己幫上了忙，非常滿足。<stop_lip_animation n00001 CLOSE_MOUTH>"
  },
  "15949": {
    "de": "",
    "en": "",
    "es": "",
    "fr": "",
    "it": "",
    "ja": "<start_lip_sync n00001 _normal m00001>「わしが　もっと　オーレンに協力できれば\n　あんな悲劇は　防げたかもしれんのに\n　わしは　できることをしなかった。<stop_lip_animation n00001 CLOSE_MOUTH>",
    "ko": "<start_lip_sync n00001 _normal m00001>: 내가 조금 더 적극적으로 오렌을 도왔다면\n　이 비극을 막을 수 있었을 거다.\n　하지만 난 내 도리를 다하지 않았어.<stop_lip_animation n00001 CLOSE_MOUTH>",
    "zh-Hans": "<start_lip_sync n00001 _normal m00001>如果我再多帮他一把，\n也许就能避免那场悲剧。\n我……没有做到自己力所能及的事。<stop_lip_animation n00001 CLOSE_MOUTH>",
    "zh-Hant": "<start_lip_sync n00001 _normal m00001>如果我再多幫他一把，\n也許就能避免那場悲劇，\n但我卻沒有去做自己力所能及的事。<stop_lip_animation n00001 CLOSE_MOUTH>"
  },
  "15950": {
    "de": "",
    "en": "",
    "es": "",
    "fr": "",
    "it": "",
    "ja": "<start_lip_sync n00001 _normal m00001>「……これは　わしの罪でも　あるのじゃ。<stop_lip_animation n00001 CLOSE_MOUTH>",
    "ko": "<start_lip_sync n00001 _normal m00001>: ……이 일은 내 책임이기도 하다.<stop_lip_animation n00001 CLOSE_MOUTH>",
    "zh-Hans": "<start_lip_sync n00001 _normal m00001>……这也是我的罪过。<stop_lip_animation n00001 CLOSE_MOUTH>",
    "zh-Hant": "<start_lip_sync n00001 _normal m00001>……這也是我的罪過。<stop_lip_animation n00001 CLOSE_MOUTH>"
  },
  "15951": {
    "de": "",
    "en": "",
    "es": "",
    "fr": "",
    "it": "",
    "ja": "<start_lip_sync n00001 _normal m00001>「部下たちに　グロリスのしずくを与えたことで\n　オーレンの無念も　消えたのじゃろう。\n　これでもう　よみがえることは　あるまい。<stop_lip_animation n00001 CLOSE_MOUTH>",
    "ko": "<start_lip_sync n00001 _normal m00001>: 부하들에게 글로리스의 물방울을 건넸으니\n　오렌의 한도 풀렸을 테지.\n　이제 오렌이 부활하는 일은 없을 거다.<stop_lip_animation n00001 CLOSE_MOUTH>",
    "zh-Hans": "<start_lip_sync n00001 _normal m00001>将古洛里斯花露给了部下，\n奥连的遗憾也就解除了。\n这下不会再复活了。<stop_lip_animation n00001 CLOSE_MOUTH>",
    "zh-Hant": "<start_lip_sync n00001 _normal m00001>將古洛里斯之露給了部下們後，\n奧連也了無遺憾了吧。\n這下應該不會再復活了。<stop_lip_animation n00001 CLOSE_MOUTH>"
  },
  "15952": {
    "de": "",
    "en": "",
    "es": "",
    "fr": "",
    "it": "",
    "ja": "<start_lip_sync n00001 _normal m00001>「あとは　この聖杯じゃが……\n　お前さん　こいつを　グレン城の\n　チグリ大臣のとこに　返してきてくれ。<stop_lip_animation n00001 CLOSE_MOUTH>",
    "ko": "<start_lip_sync n00001 _normal m00001>: 남은 건 이 성배뿐이군……\n　네가 그렌성의 치그리 대신에게\n　이걸 돌려주거라.<stop_lip_animation n00001 CLOSE_MOUTH>",
    "zh-Hans": "<start_lip_sync n00001 _normal m00001>剩下的，就是这圣杯了……\n你把它带回古莲城，\n交还给奇古力大臣吧。<stop_lip_animation n00001 CLOSE_MOUTH>",
    "zh-Hant": "<start_lip_sync n00001 _normal m00001>剩下的，就是這聖杯了……\n你把它帶回古蓮城，\n交還給奇古力大臣吧。<stop_lip_animation n00001 CLOSE_MOUTH>"
  },
  "15953": {
    "de": "",
    "en": "",
    "es": "",
    "fr": "",
    "it": "",
    "ja": "<cs_pchero>は\nレムルの聖杯（だいじなもの）を　受け取った！<me 60>",
    "ko": "{cs_pchero}|hpp(은,는)\n레물의 성배(중요한 물건)를 받았다!<me 60>",
    "zh-Hans": "<cs_pchero>收下了\n雷姆尔的圣杯（重要物品）！<me 60>",
    "zh-Hant": "<cs_pchero>收下了\n雷姆爾的聖杯（重要物品）！<me 60>"
  },
  "15954": {
    "de": "",
    "en": "",
    "es": "",
    "fr": "",
    "it": "",
    "ja": "<start_lip_sync n00001 _normal m00001>「これで　すべて　片付いた。\n　ようやく　わしも　過去の罪から\n　解放された気がする。<stop_lip_animation n00001 CLOSE_MOUTH>",
    "ko": "<start_lip_sync n00001 _normal m00001>: 이걸로 모두 마무리되었군.\n　나도 이제야 겨우 과거의 죄에서\n　해방되었단 느낌이 드는구나.<stop_lip_animation n00001 CLOSE_MOUTH>",
    "zh-Hans": "<start_lip_sync n00001 _normal m00001>这下全都结束了。\n我总算从过去的罪孽中解脱，\n如释重负了。<stop_lip_animation n00001 CLOSE_MOUTH>",
    "zh-Hant": "<start_lip_sync n00001 _normal m00001>這下全都結束了。\n我總算從過去的罪孽中解脫，\n如釋重負了。<stop_lip_animation n00001 CLOSE_MOUTH>"
  },
  "15955": {
    "de": "",
    "en": "",
    "es": "",
    "fr": "",
    "it": "",
    "ja": "<start_lip_sync n00001 _normal m00001>「それでは　わしは　ひと足先に\n　失礼させてもらうぞ！\n　達者でな　<cs_pchero>。<stop_lip_animation n00001 CLOSE_MOUTH>",
    "ko": "<start_lip_sync n00001 _normal m00001>: 그럼 난 먼저 실례하마!\n　잘 지내거라, <cs_pchero>.<stop_lip_animation n00001 CLOSE_MOUTH>",
    "zh-Hans": "<start_lip_sync n00001 _normal m00001>那我先走一步了！\n你要保重啊！\n<cs_pchero>。<stop_lip_animation n00001 CLOSE_MOUTH>",
    "zh-Hant": "<start_lip_sync n00001 _normal m00001>那我先走一步了！\n要保重啊，\n<cs_pchero>。<stop_lip_animation n00001 CLOSE_MOUTH>"
  },
  "15956": {
    "de": "",
    "en": "",
    "es": "",
    "fr": "",
    "it": "",
    "ja": "<start_lip_sync n01448 _normal m00001>「すべて　聞かせていただいたのデス。<stop_lip_animation n01448 CLOSE_MOUTH>",
    "ko": "<start_lip_sync n01448 _normal m00001>: 방금 하신 이야기, 다 들었습니다.<stop_lip_animation n01448 CLOSE_MOUTH>",
    "zh-Hans": "<start_lip_sync n01448 _normal m00001>我都听说了。<stop_lip_animation n01448 CLOSE_MOUTH>",
    "zh-Hant": "<start_lip_sync n01448 _normal m00001>我都聽說了。<stop_lip_animation n01448 CLOSE_MOUTH>"
  },
  "15957": {
    "de": "",
    "en": "",
    "es": "",
    "fr": "",
    "it": "",
    "ja": "<start_lip_sync n00004 _normal m00001>「おお　ダンデルではないか。\n　どうしたと　言うんじゃ？\n　そんな　やる気を　みなぎらせた顔をして？<stop_lip_animation n00004 CLOSE_MOUTH>",
    "ko": "<start_lip_sync n00004 _normal m00001>: 오오, 단델이군.\n　그리 의욕에 찬 얼굴로 무슨 일인가?<stop_lip_animation n00004 CLOSE_MOUTH>",
    "zh-Hans": "<start_lip_sync n00004 _normal m00001>哦，这不是丹德尔吗。\n怎么一副干劲十足的表情？\n你想说什么？<stop_lip_animation n00004 CLOSE_MOUTH>",
    "zh-Hant": "<start_lip_sync n00004 _normal m00001>喔喔，這不是丹德爾嗎？\n是怎麼了嗎？\n怎麼一副幹勁十足的表情？<stop_lip_animation n00004 CLOSE_MOUTH>"
  },
  "15958": {
    "de": "",
    "en": "",
    "es": "",
    "fr": "",
    "it": "",
    "ja": "<start_lip_sync n01448 _normal m00001>「大臣サマ。ワタクシは　決意したのデス！\n　オーレンの身に起こった　悲劇のすべてを\n　新たな歴史書に　書き残すことを！<stop_lip_animation n01448 CLOSE_MOUTH>",
    "ko": "<start_lip_sync n01448 _normal m00001>: 대신님, 전 결심했습니다!\n　오렌에게 일어난 비극의 전말을\n　새로운 역사서에 기록하기로요!<stop_lip_animation n01448 CLOSE_MOUTH>",
    "zh-Hans": "<start_lip_sync n01448 _normal m00001>大臣阁下。我心意已决！\n要把发生在奥连身上的悲剧\n全部写到新的历史书里！<stop_lip_animation n01448 CLOSE_MOUTH>",
    "zh-Hant": "<start_lip_sync n01448 _normal m00001>大臣，我心意已決！\n要把發生在奧連身上的悲劇\n全部寫到新的史書上！<stop_lip_animation n01448 CLOSE_MOUTH>"
  },
  "15959": {
    "de": "",
    "en": "",
    "es": "",
    "fr": "",
    "it": "",
    "ja": "<start_lip_sync n01448 _normal m00001>「これまで　ワタクシは　歴史を学びながらも\n　それを　どう活かすのか考えていませんでした。\n　今　はじめて　やりたいことができたのデス！<stop_lip_animation n01448 CLOSE_MOUTH>",
    "ko": "<start_lip_sync n01448 _normal m00001>: 그동안 전 역사를 연구하면서도\n　활용할 방법을 찾지 못했습니다만\n　오늘 비로소 하고 싶은 일을 찾았습니다!<stop_lip_animation n01448 CLOSE_MOUTH>",
    "zh-Hans": "<start_lip_sync n01448 _normal m00001>我学了这么久的历史，\n从没想过如何灵活运用这门知识。\n如今，我终于找到想做的事了！<stop_lip_animation n01448 CLOSE_MOUTH>",
    "zh-Hant": "<start_lip_sync n01448 _normal m00001>我學了這麼久的歷史，\n從沒想過如何活用這門知識。\n如今，我終於找到想做的事了！<stop_lip_animation n01448 CLOSE_MOUTH>"
  },
  "15960": {
    "de": "",
    "en": "",
    "es": "",
    "fr": "",
    "it": "",
    "ja": "<start_lip_sync n00004 _normal m00001>「う……うむ。\n　やりたいことが　できたのなら\n　それは　すばらしいことじゃと思うぞ。<stop_lip_animation n00004 CLOSE_MOUTH>",
    "ko": "<start_lip_sync n00004 _normal m00001>: 그…… 그렇군.\n　하고 싶은 일이 생겼다면\n　그보다 좋은 일은 없지.<stop_lip_animation n00004 CLOSE_MOUTH>",
    "zh-Hans": "<start_lip_sync n00004 _normal m00001>唔……唔。\n能做成想做的事，\n那可是很了不起的哦。<stop_lip_animation n00004 CLOSE_MOUTH>",
    "zh-Hant": "<start_lip_sync n00004 _normal m00001>唔……嗯。\n既然有想做的事，\n那可是很了不起的喔。<stop_lip_animation n00004 CLOSE_MOUTH>"
  },
  "15961": {
    "de": "",
    "en": "",
    "es": "",
    "fr": "",
    "it": "",
    "ja": "<start_lip_sync n01448 _normal m00001>「ありがとうございます　大臣サマっ！\n　それでは　さっそく　新しい歴史書の\n　執筆にとりかかるのデス！<stop_lip_animation n01448 CLOSE_MOUTH>",
    "ko": "<start_lip_sync n01448 _normal m00001>: 감사합니다, 대신님!\n　그럼 바로 새 역사서 집필에\n　착수하겠습니다!<stop_lip_animation n01448 CLOSE_MOUTH>",
    "zh-Hans": "<start_lip_sync n01448 _normal m00001>多谢您，大臣阁下！\n那我马上开始执笔新的历史书！<stop_lip_animation n01448 CLOSE_MOUTH>",
    "zh-Hant": "<start_lip_sync n01448 _normal m00001>多謝您，大臣！\n那我就立刻開始\n執筆新史書！<stop_lip_animation n01448 CLOSE_MOUTH>"
  },
  "15962": {
    "de": "",
    "en": "",
    "es": "",
    "fr": "",
    "it": "",
    "ja": "<start_lip_sync n00004 _normal m00001>「……やれやれ。まあ　これで　\n　正しい歴史が　語られるようになれば\n　オーレンも　浮かばれるというもの。<stop_lip_animation n00004 CLOSE_MOUTH>",
    "ko": "<start_lip_sync n00004 _normal m00001>: ……못 말리는 친구군. 뭐, 그래도\n　올바른 역사가 후세에 전해진다면\n　오렌도 편히 눈감을 수 있겠지요.<stop_lip_animation n00004 CLOSE_MOUTH>",
    "zh-Hans": "<start_lip_sync n00004 _normal m00001>……哎呀哎呀。这样一来\n真正的历史记入史册，\n奥连也能获得平反了呢。<stop_lip_animation n00004 CLOSE_MOUTH>",
    "zh-Hant": "<start_lip_sync n00004 _normal m00001>……真是的。不過這樣一來，\n正確的歷史開始流傳，\n奧連也能瞑目了。<stop_lip_animation n00004 CLOSE_MOUTH>"
  },
  "15963": {
    "de": "",
    "en": "",
    "es": "",
    "fr": "",
    "it": "",
    "ja": "<start_lip_sync n00004 _normal m00001>「……エイドスさまも\n　きっと　許してくださるでしょう。<stop_lip_animation n00004 CLOSE_MOUTH>",
    "ko": "<start_lip_sync n00004 _normal m00001>: ……에이도스 님도\n　기꺼이 허락해 주실 겁니다.<stop_lip_animation n00004 CLOSE_MOUTH>",
    "zh-Hans": "<start_lip_sync n00004 _normal m00001>……想必艾伊德斯大人\n也会认同这件事的。<stop_lip_animation n00004 CLOSE_MOUTH>",
    "zh-Hant": "<start_lip_sync n00004 _normal m00001>……想必艾伊德斯大人\n也會認同這件事的。<stop_lip_animation n00004 CLOSE_MOUTH>"
  }
}
